{"㍽":[{"trad":"㍽","simp":"㍽","pinyin":"xx5","defs":["大正[Da4 zheng4] written as a single character"]}],"俁":[{"trad":"俁","simp":"俣","pinyin":"yu3","defs":["big"]}],"刜":[{"trad":"刜","simp":"刜","pinyin":"fu2","defs":["to chop","strike"]}],"厮":[{"trad":"厮","simp":"厮","pinyin":"si1","defs":["variant of 廝|厮[si1]"]}],"呷":[{"trad":"呷","simp":"呷","pinyin":"xia1","defs":["to sip; to drink","Taiwan pr. [xia2]"]},{"trad":"呷呷","simp":"呷呷","pinyin":"ga1 ga1","defs":["(onom.) quack; honk"]}],"嘉":[{"trad":"嘉","simp":"嘉","pinyin":"Jia1","defs":["surname Jia"]},{"trad":"嘉","simp":"嘉","pinyin":"jia1","defs":["excellent","auspicious","to praise","to commend"]},{"trad":"嘉仁","simp":"嘉仁","pinyin":"Jia1 ren2","defs":["Yoshihito, personal name of the Taishō 大正[Da4 zheng4] emperor of Japan (1879-1926), reigned 1912-1926"]},{"trad":"嘉善","simp":"嘉善","pinyin":"Jia1 shan4","defs":["Jiashan county in Jiaxing 嘉興|嘉兴[Jia1 xing1], Zhejiang"]},{"trad":"嘉善縣","simp":"嘉善县","pinyin":"Jia1 shan4 xian4","defs":["Jiashan county in Jiaxing 嘉興|嘉兴[Jia1 xing1], Zhejiang"]},{"trad":"嘉士伯","simp":"嘉士伯","pinyin":"Jia1 shi4 bo2","defs":["Carlsberg"]},{"trad":"嘉定","simp":"嘉定","pinyin":"Jia1 ding4","defs":["Jiading district of northwest Shanghai","final reign name 1208-1224 of South Song emperor Ningzong 寧宗|宁宗[Ning2 zong1]"]},{"trad":"嘉定區","simp":"嘉定区","pinyin":"Jia1 ding4 qu1","defs":["Jiading district of northwest Shanghai"]},{"trad":"嘉寶果","simp":"嘉宝果","pinyin":"jia1 bao3 guo3","defs":["jaboticaba; Brazilian grape tree"]},{"trad":"嘉峪關","simp":"嘉峪关","pinyin":"Jia1 yu4 Guan1","defs":["Jiayu Pass in Gansu, at the western terminus of the Great Wall"]},{"trad":"嘉峪關","simp":"嘉峪关","pinyin":"Jia1 yu4 guan1","defs":["see 嘉峪關市|嘉峪关市[Jia1 yu4 guan1 Shi4]"]},{"trad":"嘉峪關城","simp":"嘉峪关城","pinyin":"Jia1 yu4 guan1 cheng2","defs":["Jiayuguan fort in the Gansu corridor","Ming dynasty military fort, the western end of the Great Wall"]},{"trad":"嘉峪關市","simp":"嘉峪关市","pinyin":"Jia1 yu4 guan1 Shi4","defs":["Jiayuguan, prefecture-level city in Gansu Province 甘肅省|甘肃省[Gan1 su4 Sheng3]"]},{"trad":"嘉年華","simp":"嘉年华","pinyin":"jia1 nian2 hua2","defs":["(loanword) carnival"]},{"trad":"嘉慶","simp":"嘉庆","pinyin":"Jia1 qing4","defs":["Jiaqing Emperor (1760-1820), seventh Qing emperor, personal name 顒琰|颙琰[Yong2 yan3], reigned 1796-1820"]},{"trad":"嘉會","simp":"嘉会","pinyin":"jia1 hui4","defs":["auspicious occasion","grand feast"]},{"trad":"嘉柏隆里","simp":"嘉柏隆里","pinyin":"Jia1 bo2 long2 li3","defs":["(Tw) Gaborone, capital of Botswana"]},{"trad":"嘉爾曼","simp":"嘉尔曼","pinyin":"Jia1 er3 man4","defs":["Carmen (name)"]},{"trad":"嘉獎","simp":"嘉奖","pinyin":"jia1 jiang3","defs":["to award","commendation","citation"]},{"trad":"嘉祥","simp":"嘉祥","pinyin":"Jia1 xiang2","defs":["Jiaxiang County in Jining 濟寧|济宁[Ji3 ning2], Shandong"]},{"trad":"嘉祥縣","simp":"嘉祥县","pinyin":"Jia1 xiang2 Xian4","defs":["Jiaxiang County in Jining 濟寧|济宁[Ji3 ning2], Shandong"]},{"trad":"嘉禾","simp":"嘉禾","pinyin":"Jia1 he2","defs":["see 嘉禾縣|嘉禾县[Jia1 he2 Xian4]"]},{"trad":"嘉禾縣","simp":"嘉禾县","pinyin":"Jia1 he2 Xian4","defs":["Jiahe, a county in Chenzhou City 郴州市[Chen1 zhou1 Shi4], Hunan"]},{"trad":"嘉義","simp":"嘉义","pinyin":"Jia1 yi4","defs":["Chiayi, a city and county in west Taiwan"]},{"trad":"嘉義市","simp":"嘉义市","pinyin":"Jia1 yi4 shi4","defs":["Chiayi city in central Taiwan"]},{"trad":"嘉義縣","simp":"嘉义县","pinyin":"Jia1 yi4 Xian4","defs":["Jiayi or Chiayi County in west Taiwan"]},{"trad":"嘉興","simp":"嘉兴","pinyin":"Jia1 xing1","defs":["see 嘉興市|嘉兴市[Jia1 xing1 Shi4]"]},{"trad":"嘉興市","simp":"嘉兴市","pinyin":"Jia1 xing1 Shi4","defs":["Jiaxing, prefecture-level city in Zhejiang Province 浙江省[Zhe4 jiang1 Sheng3]"]},{"trad":"嘉蔭","simp":"嘉荫","pinyin":"Jia1 yin1","defs":["see 嘉蔭縣|嘉荫县[Jia1 yin1 Xian4]"]},{"trad":"嘉蔭縣","simp":"嘉荫县","pinyin":"Jia1 yin1 Xian4","defs":["Jiayin, a county in Yichun City 伊春市[Yi1 chun1 Shi4], Heilongjiang"]},{"trad":"嘉許","simp":"嘉许","pinyin":"jia1 xu3","defs":["favorable","praise"]},{"trad":"嘉賓","simp":"嘉宾","pinyin":"jia1 bin1","defs":["esteemed guest","honored guest","guest (on a show)"]},{"trad":"嘉陵","simp":"嘉陵","pinyin":"Jia1 ling2","defs":["Jialing district of Nanchong city 南充市[Nan2 chong1 shi4], Sichuan"]},{"trad":"嘉陵區","simp":"嘉陵区","pinyin":"Jia1 ling2 qu1","defs":["Jialing district of Nanchong city 南充市[Nan2 chong1 shi4], Sichuan"]},{"trad":"嘉陵江","simp":"嘉陵江","pinyin":"Jia1 ling2 Jiang1","defs":["Jialing River in Sichuan (a tributary of the Yangtze)"]},{"trad":"嘉魚","simp":"嘉鱼","pinyin":"Jia1 yu2","defs":["see 嘉魚縣|嘉鱼县[Jia1 yu2 Xian4]"]},{"trad":"嘉魚縣","simp":"嘉鱼县","pinyin":"Jia1 yu2 Xian4","defs":["Jiayu, a county in Xianning City 咸寧市|咸宁市[Xian2 ning2 Shi4], Hubei"]}],"囒":[{"trad":"囒","simp":"𪢠","pinyin":"lan2","defs":["used in 囒噸|𪢠吨[Lan2 dun1]","variant of 讕|谰[lan2]","variant of 㘓|𪢌[lan2]"]},{"trad":"囒噸","simp":"𪢠吨","pinyin":"Lan2 dun1","defs":["(old) London (now written 倫敦|伦敦[Lun2 dun1])"]}],"垛":[{"trad":"垛","simp":"垛","pinyin":"duo3","defs":["battlement","target"]},{"trad":"垛","simp":"垛","pinyin":"duo4","defs":["pile"]},{"trad":"垛口","simp":"垛口","pinyin":"duo3 kou3","defs":["crenel"]}],"塤":[{"trad":"塤","simp":"埙","pinyin":"xun1","defs":["ocarina","wind instrument consisting of an egg-shaped chamber with holes"]}],"夭":[{"trad":"夭","simp":"夭","pinyin":"yao1","defs":["(bound form) to die prematurely (also pr. [yao3])","(literary) (of vegetation) luxuriant"]},{"trad":"夭亡","simp":"夭亡","pinyin":"yao1 wang2","defs":["to die young"]},{"trad":"夭壽","simp":"夭寿","pinyin":"yao1 shou4","defs":["to die young","(Tw) (curse word) drop dead","go to hell","(literary) short life and long life"]},{"trad":"夭折","simp":"夭折","pinyin":"yao1 zhe2","defs":["to die young or prematurely","to come to a premature end","to be aborted prematurely"]},{"trad":"夭殤","simp":"夭殇","pinyin":"yao1 shang1","defs":["to die young"]}],"姶":[{"trad":"姶","simp":"姶","pinyin":"e4","defs":["wonderful","beautiful","(used in female given names and as a surname)"]}],"媿":[{"trad":"媿","simp":"愧","pinyin":"kui4","defs":["old variant of 愧[kui4]"]}],"守":[{"trad":"守","simp":"守","pinyin":"shou3","defs":["to guard","to defend","to keep watch","to abide by the law","to observe (rules or ritual)","nearby","adjoining"]},{"trad":"守一而終","simp":"守一而终","pinyin":"shou3 yi1 er2 zhong1","defs":["to be faithful to one's mate all one's life"]},{"trad":"守住","simp":"守住","pinyin":"shou3 zhu5","defs":["to hold on to","to defend","to keep","to guard"]},{"trad":"守信","simp":"守信","pinyin":"shou3 xin4","defs":["to keep promises"]},{"trad":"守信用","simp":"守信用","pinyin":"shou3 xin4 yong4","defs":["to keep one's word","trustworthy"]},{"trad":"守候","simp":"守候","pinyin":"shou3 hou4","defs":["to wait for","to expect","to keep watch","to watch over","to nurse"]},{"trad":"守備","simp":"守备","pinyin":"shou3 bei4","defs":["to garrison","to stand guard","on garrison duty"]},{"trad":"守兵","simp":"守兵","pinyin":"shou3 bing1","defs":["guard","garrison soldier"]},{"trad":"守分","simp":"守分","pinyin":"shou3 fen4","defs":["to abide by the law","to respect the law"]},{"trad":"守制","simp":"守制","pinyin":"shou3 zhi4","defs":["to go into mourning for one's parents"]},{"trad":"守則","simp":"守则","pinyin":"shou3 ze2","defs":["rules","regulations"]},{"trad":"守勢","simp":"守势","pinyin":"shou3 shi4","defs":["defensive position","guard"]},{"trad":"守口如瓶","simp":"守口如瓶","pinyin":"shou3 kou3 ru2 ping2","defs":["lit. to guard one's mouth like a closed bottle (idiom); tight-lipped","reticent","not breathing a word"]},{"trad":"守喪","simp":"守丧","pinyin":"shou3 sang1","defs":["to keep watch beside a coffin","to observe a period of mourning"]},{"trad":"守土","simp":"守土","pinyin":"shou3 tu3","defs":["to guard one's territory","to protect the country"]},{"trad":"守土有責","simp":"守土有责","pinyin":"shou3 tu3 you3 ze2","defs":["duty to defend the country (idiom)"]},{"trad":"守夜","simp":"守夜","pinyin":"shou3 ye4","defs":["to be on all-night duty","to be on night watch","to keep a vigil"]},{"trad":"守孝","simp":"守孝","pinyin":"shou3 xiao4","defs":["to observe mourning for one's parents"]},{"trad":"守宮","simp":"守宫","pinyin":"shou3 gong1","defs":["gecko; house lizard"]},{"trad":"守寡","simp":"守寡","pinyin":"shou3 gua3","defs":["to live as widow","to observe widowhood"]},{"trad":"守恆","simp":"守恒","pinyin":"shou3 heng2","defs":["conservation (e.g. of energy, momentum or heat in physics)","to remain constant (of a number)"]},{"trad":"守恆定律","simp":"守恒定律","pinyin":"shou3 heng2 ding4 lu:4","defs":["conservation law (physics)"]},{"trad":"守成","simp":"守成","pinyin":"shou3 cheng2","defs":["to preserve the accomplishments of previous generations","to carry on the good work of one's predecessors"]},{"trad":"守拙","simp":"守拙","pinyin":"shou3 zhuo1","defs":["to remain honest and poor"]},{"trad":"守敵","simp":"守敌","pinyin":"shou3 di2","defs":["enemy defense","enemy garrison"]},{"trad":"守時","simp":"守时","pinyin":"shou3 shi2","defs":["punctual"]},{"trad":"守更","simp":"守更","pinyin":"shou3 geng1","defs":["to keep watch during the night"]},{"trad":"守服","simp":"守服","pinyin":"shou3 fu2","defs":["to observe mourning for one's parents"]},{"trad":"守望","simp":"守望","pinyin":"shou3 wang4","defs":["to keep watch"]},{"trad":"守望台","simp":"守望台","pinyin":"shou3 wang4 tai2","defs":["watchtower"]},{"trad":"守望相助","simp":"守望相助","pinyin":"shou3 wang4 xiang1 zhu4","defs":["to keep watch and defend one another (idiom, from Mencius); to join forces to defend against external aggressors","mutual help and protection"]},{"trad":"守株待兔","simp":"守株待兔","pinyin":"shou3 zhu1 dai4 tu4","defs":["lit. to guard a tree-stump, waiting for rabbits (idiom)","to wait idly for opportunities","to trust to chance rather than show initiative"]},{"trad":"守株待兔，緣木求魚","simp":"守株待兔，缘木求鱼","pinyin":"shou3 zhu1 dai4 tu4 , yuan2 mu4 qiu2 yu2","defs":["to guard a tree-stump, waiting for rabbits, and climb a tree to catch fish (idiom); without any practical course of action"]},{"trad":"守株緣木","simp":"守株缘木","pinyin":"shou3 zhu1 yuan2 mu4","defs":["abbr. for 守株待兔，緣木求魚|守株待兔，缘木求鱼[shou3 zhu1 dai4 tu4 , yuan2 mu4 qiu2 yu2]"]},{"trad":"守業","simp":"守业","pinyin":"shou3 ye4","defs":["to preserve one's heritage","to defend the accomplishments of previous generations","to carry on the good work","to keep one's business going"]},{"trad":"守正不阿","simp":"守正不阿","pinyin":"shou3 zheng4 bu4 e1","defs":["to be strictly just and impartial"]},{"trad":"守歲","simp":"守岁","pinyin":"shou3 sui4","defs":["to see in the New Year","to stay up all night on lunar New Year's Eve"]},{"trad":"守法","simp":"守法","pinyin":"shou3 fa3","defs":["to abide by the law"]},{"trad":"守活寡","simp":"守活寡","pinyin":"shou3 huo2 gua3","defs":["to stay at home while one's husband is away","grass widow"]},{"trad":"守禦","simp":"守御","pinyin":"shou3 yu4","defs":["to defend"]},{"trad":"守空房","simp":"守空房","pinyin":"shou3 kong1 fang2","defs":["to stay home alone (of married woman)"]},{"trad":"守節","simp":"守节","pinyin":"shou3 jie2","defs":["faithful (to the memory of betrothed)","constant (of widow who remains unmarried)"]},{"trad":"守約","simp":"守约","pinyin":"shou3 yue1","defs":["to keep an appointment","to keep one's word"]},{"trad":"守職","simp":"守职","pinyin":"shou3 zhi2","defs":["to observe one's duty steadfastly","devoted to one's job"]},{"trad":"守舊","simp":"守旧","pinyin":"shou3 jiu4","defs":["conservative","reactionary"]},{"trad":"守舊派","simp":"守旧派","pinyin":"shou3 jiu4 pai4","defs":["person who sticks to old ways; a diehard; a conservative"]},{"trad":"守衛","simp":"守卫","pinyin":"shou3 wei4","defs":["to guard","to defend"]},{"trad":"守衛者","simp":"守卫者","pinyin":"shou3 wei4 zhe3","defs":["defender","a guard"]},{"trad":"守規矩","simp":"守规矩","pinyin":"shou3 gui1 ju5","defs":["to behave oneself; to abide by the rules"]},{"trad":"守護","simp":"守护","pinyin":"shou3 hu4","defs":["to guard","to protect"]},{"trad":"守護神","simp":"守护神","pinyin":"shou3 hu4 shen2","defs":["protector God","patron saint"]},{"trad":"守財奴","simp":"守财奴","pinyin":"shou3 cai2 nu2","defs":["miser","scrooge"]},{"trad":"守身","simp":"守身","pinyin":"shou3 shen1","defs":["to keep oneself pure","to preserve one's integrity","to remain chaste"]},{"trad":"守身如玉","simp":"守身如玉","pinyin":"shou3 shen1 ru2 yu4","defs":["to keep oneself pure","to preserve one's integrity","to remain chaste"]},{"trad":"守車","simp":"守车","pinyin":"shou3 che1","defs":["guard's van (on train)","caboose"]},{"trad":"守軍","simp":"守军","pinyin":"shou3 jun1","defs":["defenders"]},{"trad":"守門","simp":"守门","pinyin":"shou3 men2","defs":["to keep goal","on duty as gatekeeper"]},{"trad":"守門人","simp":"守门人","pinyin":"shou3 men2 ren2","defs":["gatekeeper"]},{"trad":"守門員","simp":"守门员","pinyin":"shou3 men2 yuan2","defs":["goalkeeper"]},{"trad":"守靈","simp":"守灵","pinyin":"shou3 ling2","defs":["to keep watch beside a coffin"]},{"trad":"守齋","simp":"守斋","pinyin":"shou3 zhai1","defs":["to fast"]}],"屑":[{"trad":"屑","simp":"屑","pinyin":"xie4","defs":["bits","fragments","crumbs","filings","trifling","trivial","to condescend to"]}],"崚":[{"trad":"崚","simp":"崚","pinyin":"leng2","defs":["lofty (as of mountain)"]}],"巣":[{"trad":"巣","simp":"巣","pinyin":"chao2","defs":["Japanese variant of 巢"]}],"庬":[{"trad":"庬","simp":"庬","pinyin":"pang2","defs":["huge"]}],"懐":[{"trad":"懐","simp":"懐","pinyin":"huai2","defs":["Japanese variant of 懷|怀[huai2]"]}],"擴":[{"trad":"擴","simp":"扩","pinyin":"kuo4","defs":["to enlarge"]},{"trad":"擴充","simp":"扩充","pinyin":"kuo4 chong1","defs":["to expand"]},{"trad":"擴列","simp":"扩列","pinyin":"kuo4 lie4","defs":["(Internet slang) to add a friend (on a social network etc)"]},{"trad":"擴印","simp":"扩印","pinyin":"kuo4 yin4","defs":["to enlarge (a photo)","to print larger"]},{"trad":"擴及","simp":"扩及","pinyin":"kuo4 ji2","defs":["to extend to"]},{"trad":"擴增","simp":"扩增","pinyin":"kuo4 zeng1","defs":["to augment","to amplify","to extend","to expand"]},{"trad":"擴增實境","simp":"扩增实境","pinyin":"kuo4 zeng1 shi2 jing4","defs":["augmented reality (computing)"]},{"trad":"擴大","simp":"扩大","pinyin":"kuo4 da4","defs":["to expand","to enlarge","to broaden one's scope"]},{"trad":"擴大再生產","simp":"扩大再生产","pinyin":"kuo4 da4 zai4 sheng1 chan3","defs":["to expand production","to reproduce on an extended scale"]},{"trad":"擴大化","simp":"扩大化","pinyin":"kuo4 da4 hua4","defs":["to extend the scope","to exaggerate"]},{"trad":"擴孔","simp":"扩孔","pinyin":"kuo4 kong3","defs":["to widen a tube","to ream (i.e. widen a hole)"]},{"trad":"擴容","simp":"扩容","pinyin":"kuo4 rong2","defs":["to ramp up capacity","to expand in scale"]},{"trad":"擴展","simp":"扩展","pinyin":"kuo4 zhan3","defs":["to extend","to expand","extension","expansion"]},{"trad":"擴展名","simp":"扩展名","pinyin":"kuo4 zhan3 ming2","defs":["(file) extension (computing)"]},{"trad":"擴展塢","simp":"扩展坞","pinyin":"kuo4 zhan3 wu4","defs":["docking station"]},{"trad":"擴展程序","simp":"扩展程序","pinyin":"kuo4 zhan3 cheng2 xu4","defs":["(computing) extension (for a software application, esp. web browsers)"]},{"trad":"擴建","simp":"扩建","pinyin":"kuo4 jian4","defs":["to extend (a building, an airport runway etc)"]},{"trad":"擴張","simp":"扩张","pinyin":"kuo4 zhang1","defs":["expansion","dilation","to expand (e.g. one's power or influence)","to broaden"]},{"trad":"擴散","simp":"扩散","pinyin":"kuo4 san4","defs":["to spread; to proliferate; to diffuse"]},{"trad":"擴散周知","simp":"扩散周知","pinyin":"kuo4 san4 zhou1 zhi1","defs":["to let everyone know","spread the word!"]},{"trad":"擴版","simp":"扩版","pinyin":"kuo4 ban3","defs":["to increase the number of pages or the size of the pages of a publication"]},{"trad":"擴編","simp":"扩编","pinyin":"kuo4 bian1","defs":["to expand (esp. by new recruitment)","to increase the army","to augment"]},{"trad":"擴胸器","simp":"扩胸器","pinyin":"kuo4 xiong1 qi4","defs":["chest expander (exercise equipment)"]},{"trad":"擴表","simp":"扩表","pinyin":"kuo4 biao3","defs":["to expand the balance sheet"]},{"trad":"擴軍","simp":"扩军","pinyin":"kuo4 jun1","defs":["armament","to expand armed forces"]},{"trad":"擴音","simp":"扩音","pinyin":"kuo4 yin1","defs":["to amplify (sound)"]},{"trad":"擴音器","simp":"扩音器","pinyin":"kuo4 yin1 qi4","defs":["megaphone","loudspeaker","amplifier","microphone"]},{"trad":"擴音機","simp":"扩音机","pinyin":"kuo4 yin1 ji1","defs":["amplifier","loudspeaker","hearing aid"]}],"施":[{"trad":"施","simp":"施","pinyin":"Shi1","defs":["surname Shi"]},{"trad":"施","simp":"施","pinyin":"shi1","defs":["(bound form) to put into effect (regulations etc)","to distribute (alms etc)","to apply (fertilizer etc)"]},{"trad":"施主","simp":"施主","pinyin":"shi1 zhu3","defs":["benefactor (term used by a monk to address a layperson)","donor (semiconductor)"]},{"trad":"施主能級","simp":"施主能级","pinyin":"shi1 zhu3 neng2 ji2","defs":["donor level (semiconductor)"]},{"trad":"施予","simp":"施予","pinyin":"shi1 yu3","defs":["variant of 施與|施与[shi1 yu3]"]},{"trad":"施事","simp":"施事","pinyin":"shi1 shi4","defs":["(linguistics) agent; doer"]},{"trad":"施事者","simp":"施事者","pinyin":"shi1 shi4 zhe3","defs":["(linguistics) agent; doer"]},{"trad":"施以","simp":"施以","pinyin":"shi1 yi3","defs":["to inflict (punishment)","to provide (training etc)","to apply (pressure etc)"]},{"trad":"施加","simp":"施加","pinyin":"shi1 jia1","defs":["to exert (effort or pressure)"]},{"trad":"施壓","simp":"施压","pinyin":"shi1 ya1","defs":["to pressure"]},{"trad":"施密特","simp":"施密特","pinyin":"Shi1 mi4 te4","defs":["Schmidt or Schmitt (surname)"]},{"trad":"施展","simp":"施展","pinyin":"shi1 zhan3","defs":["to use fully","to put to use"]},{"trad":"施工","simp":"施工","pinyin":"shi1 gong1","defs":["construction","to carry out construction or large-scale repairs"]},{"trad":"施工單位","simp":"施工单位","pinyin":"shi1 gong1 dan1 wei4","defs":["unit in charge of construction","builder"]},{"trad":"施恩","simp":"施恩","pinyin":"shi1 en1","defs":["to confer a favor on sb","to confer a benefit"]},{"trad":"施惠","simp":"施惠","pinyin":"shi1 hui4","defs":["to give charity to sb","to oblige"]},{"trad":"施打","simp":"施打","pinyin":"shi1 da3","defs":["to inject (a vaccine etc)"]},{"trad":"施捨","simp":"施舍","pinyin":"shi1 she3","defs":["to give in charity","to give alms (to the poor)"]},{"trad":"施放","simp":"施放","pinyin":"shi1 fang4","defs":["to fire","to discharge","to release (fireworks, smokescreen, poison gas, virus etc)"]},{"trad":"施政","simp":"施政","pinyin":"shi1 zheng4","defs":["administration"]},{"trad":"施政報告","simp":"施政报告","pinyin":"shi1 zheng4 bao4 gao4","defs":["administrative report"]},{"trad":"施救","simp":"施救","pinyin":"shi1 jiu4","defs":["to rescue; to render emergency aid"]},{"trad":"施教","simp":"施教","pinyin":"shi1 jiao4","defs":["teaching"]},{"trad":"施明德","simp":"施明德","pinyin":"Shi1 Ming2 de2","defs":["Shih Ming-teh (1941–2024), Taiwanese politician, imprisoned 1962–1977 and 1980–1990 under the Guomindang, subsequently a leader of DPP 民進黨|民进党[Min2 jin4 dang3], in 2006 led protests against Chen Shui-Bian 陳水扁|陈水扁[Chen2 Shui3 bian3]"]},{"trad":"施暴","simp":"施暴","pinyin":"shi1 bao4","defs":["to use violence; to attack; to assault"]},{"trad":"施樂","simp":"施乐","pinyin":"Shi1 le4","defs":["Xerox"]},{"trad":"施治","simp":"施治","pinyin":"shi1 zhi4","defs":["to apply a treatment; to undertake a therapy"]},{"trad":"施法","simp":"施法","pinyin":"shi1 fa3","defs":["to implement the law","to perform sorcery"]},{"trad":"施泰爾馬克","simp":"施泰尔马克","pinyin":"Shi1 tai4 er3 ma3 ke4","defs":["Styria (Steiermark), province of Austria"]},{"trad":"施洗","simp":"施洗","pinyin":"shi1 xi3","defs":["baptize"]},{"trad":"施洗約翰","simp":"施洗约翰","pinyin":"Shi1 xi3 Yue1 han4","defs":["John the Baptist"]},{"trad":"施洗者約翰","simp":"施洗者约翰","pinyin":"Shi1 xi3 zhe3 Yue1 han4","defs":["John the Baptist"]},{"trad":"施特勞斯","simp":"施特劳斯","pinyin":"Shi1 te4 lao2 si1","defs":["Strauss (name)","Johann Strauss (1825-1899), Austrian composer","Richard Strauss (1864-1949), German composer"]},{"trad":"施琅","simp":"施琅","pinyin":"Shi1 Lang2","defs":["Shi Lang (1621–1696), Chinese admiral who served under the Ming and Qing dynasties"]},{"trad":"施瓦布","simp":"施瓦布","pinyin":"Shi1 wa3 bu4","defs":["Schwab (name)"]},{"trad":"施瓦辛格","simp":"施瓦辛格","pinyin":"Shi1 wa3 xin1 ge2","defs":["Arnold Schwarzenegger (1947-), US actor and politician, governor of California 2003-2011"]},{"trad":"施用","simp":"施用","pinyin":"shi1 yong4","defs":["to implement","to use"]},{"trad":"施甸","simp":"施甸","pinyin":"Shi1 dian4","defs":["Shidian county in Baoshan 保山[Bao3 shan1], Yunnan"]},{"trad":"施甸縣","simp":"施甸县","pinyin":"Shi1 dian4 xian4","defs":["Shidian county in Baoshan 保山[Bao3 shan1], Yunnan"]},{"trad":"施禮","simp":"施礼","pinyin":"shi1 li3","defs":["to salute","to greet"]},{"trad":"施秉","simp":"施秉","pinyin":"Shi1 bing3","defs":["see 施秉縣|施秉县[Shi1 bing3 Xian4]"]},{"trad":"施秉縣","simp":"施秉县","pinyin":"Shi1 bing3 Xian4","defs":["Shibing, a county in Qiandongnan Miao and Dong Autonomous Prefecture 黔東南苗族侗族自治州|黔东南苗族侗族自治州[Qian2 dong1 nan2 Miao2 zu2 Dong4 zu2 Zi4 zhi4 zhou1], Guizhou"]},{"trad":"施粥捨飯","simp":"施粥舍饭","pinyin":"shi1 zhou1 she3 fan4","defs":["to provide alms and rice (idiom)"]},{"trad":"施羅德","simp":"施罗德","pinyin":"Shi1 luo2 de2","defs":["(name) Schröder","Gerhard Schröder (1944–), German SPD politician, Chancellor 1998–2005"]},{"trad":"施耐庵","simp":"施耐庵","pinyin":"Shi1 Nai4 an1","defs":["Shi Nai'an (1296-1371), author of Water Margin or Outlaws of the Marsh 水滸傳|水浒传[Shui3 hu3 Zhuan4]"]},{"trad":"施肥","simp":"施肥","pinyin":"shi1 fei2","defs":["to apply fertilizer"]},{"trad":"施與","simp":"施与","pinyin":"shi1 yu3","defs":["to donate","to give","to grant","to distribute","to administer"]},{"trad":"施華洛世奇水晶","simp":"施华洛世奇水晶","pinyin":"Shi1 hua2 luo4 shi4 qi2 shui3 jing1","defs":["Swarovski crystal"]},{"trad":"施虐","simp":"施虐","pinyin":"shi1 nu:e4","defs":["to torment; to abuse (an animal, child etc)"]},{"trad":"施虐受虐","simp":"施虐受虐","pinyin":"shi1 nu:e4 shou4 nu:e4","defs":["sado-masochism"]},{"trad":"施虐狂","simp":"施虐狂","pinyin":"shi1 nu:e4 kuang2","defs":["sadism (psychiatry)"]},{"trad":"施虐癖","simp":"施虐癖","pinyin":"shi1 nu:e4 pi3","defs":["sadism (fetish)"]},{"trad":"施虐者","simp":"施虐者","pinyin":"shi1 nu:e4 zhe3","defs":["abuser","(in sadomasochism) dominant partner"]},{"trad":"施行","simp":"施行","pinyin":"shi1 xing2","defs":["to put in place","to put into practice","to take effect"]},{"trad":"施食","simp":"施食","pinyin":"shi1 shi2","defs":["to give food (as a charity)","\"feeding the hungry ghosts\" (Buddhist ceremony)"]}],"暆":[{"trad":"暆","simp":"暆","pinyin":"yi2","defs":["(of the sun) declining"]}],"杏":[{"trad":"杏","simp":"杏","pinyin":"xing4","defs":["apricot","(bound form) almond"]},{"trad":"杏仁","simp":"杏仁","pinyin":"xing4 ren2","defs":["almond","apricot kernel"]},{"trad":"杏仁果","simp":"杏仁果","pinyin":"xing4 ren2 guo3","defs":["(Tw) almond"]},{"trad":"杏仁核","simp":"杏仁核","pinyin":"xing4 ren2 he2","defs":["amygdala"]},{"trad":"杏仁豆腐","simp":"杏仁豆腐","pinyin":"xing4 ren2 dou4 fu5","defs":["almond tofu; almond jelly (dessert made with apricot kernel milk, sugar and agar)"]},{"trad":"杏仁體","simp":"杏仁体","pinyin":"xing4 ren2 ti3","defs":["amygdala"]},{"trad":"杏子","simp":"杏子","pinyin":"xing4 zi5","defs":["apricot"]},{"trad":"杏林","simp":"杏林","pinyin":"Xing4 lin2","defs":["Xinglin District of Xiamen city (renamed Haicang 海滄區|海沧区[Hai3 cang1 Qu1] in 2003)"]},{"trad":"杏林","simp":"杏林","pinyin":"xing4 lin2","defs":["forest of apricot trees","(fig.) honorific term for fine doctor (cf Dr Dong Feng 董奉[Dong3 Feng4], 3rd century AD, asked his patients to plant apricot trees instead of paying fees)"]},{"trad":"杏林區","simp":"杏林区","pinyin":"Xing4 lin2 Qu1","defs":["Xinglin District of Xiamen city 廈門市|厦门市[Xia4 men2 shi4] (renamed Haicang District 海滄區|海沧区[Hai3 cang1 Qu1] in 2003)"]},{"trad":"杏樹","simp":"杏树","pinyin":"xing4 shu4","defs":["apricot tree"]},{"trad":"杏眼","simp":"杏眼","pinyin":"xing4 yan3","defs":["large, round eyes (considered beautiful)"]},{"trad":"杏花嶺","simp":"杏花岭","pinyin":"Xing4 hua1 ling3","defs":["Xinghualing district of Taiyuan city 太原市[Tai4 yuan2 shi4], Shanxi"]},{"trad":"杏花嶺區","simp":"杏花岭区","pinyin":"Xing4 hua1 ling3 qu1","defs":["Xinghualing district of Taiyuan city 太原市[Tai4 yuan2 shi4], Shanxi"]},{"trad":"杏花村","simp":"杏花村","pinyin":"xing4 hua1 cun1","defs":["village of blossoming apricot trees where one can find a wineshop (reference to the famous poem 清明 by 杜牧[Du4 Mu4])"]},{"trad":"杏鮑菇","simp":"杏鲍菇","pinyin":"xing4 bao4 gu1","defs":["king oyster mushroom (Pleurotus eryngii)"]}],"栘":[{"trad":"栘","simp":"栘","pinyin":"yi2","defs":["shadbush or shadberry (genus Amelanchier)","name for a stable during the Han Dynasty"]}],"榪":[{"trad":"榪","simp":"杩","pinyin":"ma4","defs":["headboard"]}],"欼":[{"trad":"欼","simp":"欼","pinyin":"chi3","defs":["drink"]}],"氅":[{"trad":"氅","simp":"氅","pinyin":"chang3","defs":["overcoat"]}],"漩":[{"trad":"漩","simp":"漩","pinyin":"xuan2","defs":["whirlpool","eddy","also pr. [xuan4]"]},{"trad":"漩渦","simp":"漩涡","pinyin":"xuan2 wo1","defs":["whirlpool","eddy","vortex","(fig.) maelstrom"]}],"濲":[{"trad":"濲","simp":"濲","pinyin":"gu3","defs":["name of a river in Hunan"]}],"炻":[{"trad":"炻","simp":"炻","pinyin":"shi2","defs":["stoneware"]},{"trad":"炻器","simp":"炻器","pinyin":"shi2 qi4","defs":["stoneware"]}],"熄":[{"trad":"熄","simp":"熄","pinyin":"xi1","defs":["to extinguish","to put out (fire)","to quench","to stop burning","to go out (of fire, lamp etc)","to come to an end","to wither away","to die out","Taiwan pr. [xi2]"]},{"trad":"熄屏","simp":"熄屏","pinyin":"xi1 ping2","defs":["variant of 息屏[xi1 ping2]"]},{"trad":"熄滅","simp":"熄灭","pinyin":"xi1 mie4","defs":["to stop burning","to go out (of fire)","to die out","extinguished"]},{"trad":"熄火","simp":"熄火","pinyin":"xi1 huo3","defs":["(of fire, lamp etc) to go out","to put out (fire)","(fig.) to die down","(of a vehicle) to stall"]},{"trad":"熄燈","simp":"熄灯","pinyin":"xi1 deng1","defs":["turn out the lights","lights out"]}],"猖":[{"trad":"猖","simp":"猖","pinyin":"chang1","defs":["ferocious"]},{"trad":"猖亂","simp":"猖乱","pinyin":"chang1 luan4","defs":["wild and disorderly"]},{"trad":"猖厲","simp":"猖厉","pinyin":"chang1 li4","defs":["mad and violent"]},{"trad":"猖披","simp":"猖披","pinyin":"chang1 pi1","defs":["dishevelled","wild","unrestrained"]},{"trad":"猖狂","simp":"猖狂","pinyin":"chang1 kuang2","defs":["savage","furious"]},{"trad":"猖猖狂狂","simp":"猖猖狂狂","pinyin":"chang1 chang1 kuang2 kuang2","defs":["wild","hurried and confused","hell-for-leather"]},{"trad":"猖獗","simp":"猖獗","pinyin":"chang1 jue2","defs":["to be rampant","to run wild"]}],"璨":[{"trad":"璨","simp":"璨","pinyin":"can4","defs":["gem","luster of gem"]},{"trad":"璨玉","simp":"璨玉","pinyin":"can4 yu4","defs":["lustrous jade"]},{"trad":"璨璨","simp":"璨璨","pinyin":"can4 can4","defs":["very bright"]},{"trad":"璨美","simp":"璨美","pinyin":"can4 mei3","defs":["resplendent"]}],"畱":[{"trad":"畱","simp":"留","pinyin":"liu2","defs":["old variant of 留[liu2]"]}],"瘺":[{"trad":"瘺","simp":"瘺","pinyin":"lou4","defs":["variant of 瘻|瘘[lou4]"]}],"神":[{"trad":"神","simp":"神","pinyin":"Shen2","defs":["God"]},{"trad":"神","simp":"神","pinyin":"shen2","defs":["god; deity","supernatural; magical; mysterious","spirit; mind; energy","lively; expressive","look; expression","(coll.) awesome; amazing"]},{"trad":"神不守舍","simp":"神不守舍","pinyin":"shen2 bu4 shou3 she4","defs":["(idiom) absentminded; dazed; distracted"]},{"trad":"神不知鬼不覺","simp":"神不知鬼不觉","pinyin":"shen2 bu4 zhi1 gui3 bu4 jue2","defs":["top secret","hush-hush"]},{"trad":"神乎其技","simp":"神乎其技","pinyin":"shen2 hu1 qi2 ji4","defs":["(idiom) brilliant","extremely skillful","virtuosic"]},{"trad":"神交","simp":"神交","pinyin":"shen2 jiao1","defs":["soul brothers","friends in spirit who have never met","to commune with"]},{"trad":"神人","simp":"神人","pinyin":"shen2 ren2","defs":["God","deity"]},{"trad":"神仙","simp":"神仙","pinyin":"shen2 xian1","defs":["Daoist immortal","supernatural entity","(in modern fiction) fairy, elf, leprechaun etc","fig. lighthearted person"]},{"trad":"神似","simp":"神似","pinyin":"shen2 si4","defs":["similar in expression and spirit","to bear a remarkable resemblance to"]},{"trad":"神位","simp":"神位","pinyin":"shen2 wei4","defs":["spirit tablet","ancestral tablet"]},{"trad":"神佛","simp":"神佛","pinyin":"Shen2 Fo2","defs":["Gods and Buddhas"]},{"trad":"神作","simp":"神作","pinyin":"shen2 zuo4","defs":["(slang) masterpiece"]},{"trad":"神偷","simp":"神偷","pinyin":"shen2 tou1","defs":["master thief"]},{"trad":"神傷","simp":"神伤","pinyin":"shen2 shang1","defs":["depressed","dispirited","dejected"]},{"trad":"神像","simp":"神像","pinyin":"shen2 xiang4","defs":["likeness of a god or Buddha","(old) portrait of the deceased"]},{"trad":"神入","simp":"神入","pinyin":"shen2 ru4","defs":["(psychology) empathy","to empathize with"]},{"trad":"神出鬼沒","simp":"神出鬼没","pinyin":"shen2 chu1 gui3 mo4","defs":["lit. to appear and disappear unpredictably like a spirit or a ghost (idiom)","fig. elusive"]},{"trad":"神力","simp":"神力","pinyin":"shen2 li4","defs":["occult force","the power of a God or spirit"]},{"trad":"神功","simp":"神功","pinyin":"shen2 gong1","defs":["amazing powers","miraculous skill"]},{"trad":"神勇","simp":"神勇","pinyin":"shen2 yong3","defs":["extraordinarily brave","heroic"]},{"trad":"神勞形瘁","simp":"神劳形瘁","pinyin":"shen2 lao2 xing2 cui4","defs":["to be completely drained both emotionally and physically (idiom)"]},{"trad":"神化","simp":"神化","pinyin":"shen2 hua4","defs":["to make divine","apotheosis"]},{"trad":"神器","simp":"神器","pinyin":"shen2 qi4","defs":["magical object","object symbolic of imperial power","fine weapon","very useful tool"]},{"trad":"神奇","simp":"神奇","pinyin":"shen2 qi2","defs":["magical","mystical","miraculous"]},{"trad":"神奇寶貝","simp":"神奇宝贝","pinyin":"Shen2 qi2 Bao3 bei4","defs":["Pokémon or Pocket Monsters, popular Japanese video game, anime and manga"]},{"trad":"神奈川","simp":"神奈川","pinyin":"Shen2 nai4 chuan1","defs":["Kanagawa, Japan"]},{"trad":"神奈川縣","simp":"神奈川县","pinyin":"Shen2 nai4 chuan1 xian4","defs":["Kanagawa prefecture, Japan"]},{"trad":"神奧","simp":"神奥","pinyin":"shen2 ao4","defs":["mysterious","an enigma"]},{"trad":"神女","simp":"神女","pinyin":"Shen2 nu:3","defs":["The Goddess, 1934 silent film about a Shanghai prostitute, directed by 吳永剛|吴永刚[Wu2 Yong3 gang1]"]},{"trad":"神女","simp":"神女","pinyin":"shen2 nu:3","defs":["goddess","(old) prostitute"]},{"trad":"神女峰","simp":"神女峰","pinyin":"Shen2 nu:3 Feng1","defs":["name of a peak by the Three Gorges 長江三峽|长江三峡[Chang2 Jiang1 San1 xia2]"]},{"trad":"神女有心，襄王無夢","simp":"神女有心，襄王无梦","pinyin":"shen2 nu:3 you3 xin1 , Xiang1 Wang2 wu2 meng4","defs":["lit. the fairy is willing, but King Xiang doesn't dream (idiom)","(said of a woman's unrequited love)"]},{"trad":"神妙","simp":"神妙","pinyin":"shen2 miao4","defs":["marvelous","wondrous"]},{"trad":"神學","simp":"神学","pinyin":"shen2 xue2","defs":["theological","theology"]},{"trad":"神學士","simp":"神学士","pinyin":"shen2 xue2 shi4","defs":["student of theology","Bachelor of Divinity","Taleban (Farsi: student)"]},{"trad":"神學家","simp":"神学家","pinyin":"shen2 xue2 jia1","defs":["theologian"]},{"trad":"神學研究所","simp":"神学研究所","pinyin":"shen2 xue2 yan2 jiu1 suo3","defs":["seminary"]},{"trad":"神學院","simp":"神学院","pinyin":"shen2 xue2 yuan4","defs":["seminary"]},{"trad":"神山","simp":"神山","pinyin":"shen2 shan1","defs":["sacred mountain"]},{"trad":"神州","simp":"神州","pinyin":"Shen2 zhou1","defs":["old name for China"]},{"trad":"神工鬼斧","simp":"神工鬼斧","pinyin":"shen2 gong1 gui3 fu3","defs":["supernaturally fine craft (idiom); the work of the Gods","uncanny workmanship","superlative craftsmanship"]},{"trad":"神差鬼使","simp":"神差鬼使","pinyin":"shen2 chai1 gui3 shi3","defs":["the work of gods and devils (idiom); unexplained event crying out for a supernatural explanation","curious coincidence"]},{"trad":"神廚","simp":"神厨","pinyin":"shen2 chu2","defs":["master chef"]},{"trad":"神廟","simp":"神庙","pinyin":"shen2 miao4","defs":["temple"]},{"trad":"神往","simp":"神往","pinyin":"shen2 wang3","defs":["to be fascinated","to be rapt","to long for","to dream of"]},{"trad":"神志","simp":"神志","pinyin":"shen2 zhi4","defs":["consciousness","state of mind","compos mentis"]},{"trad":"神志不清","simp":"神志不清","pinyin":"shen2 zhi4 bu4 qing1","defs":["to be delirious","to be mentally confused"]},{"trad":"神志昏迷","simp":"神志昏迷","pinyin":"shen2 zhi4 hun1 mi2","defs":["to be in a state of delirium"]},{"trad":"神思","simp":"神思","pinyin":"shen2 si1","defs":["state of mind"]},{"trad":"神思恍惚","simp":"神思恍惚","pinyin":"shen2 si1 huang3 hu1","defs":["abstracted","absent-minded","in a trance"]},{"trad":"神性","simp":"神性","pinyin":"shen2 xing4","defs":["divinity"]},{"trad":"神怪","simp":"神怪","pinyin":"shen2 guai4","defs":["spirits and devils (usually harmful)","demon"]},{"trad":"神情","simp":"神情","pinyin":"shen2 qing2","defs":["look; expression"]},{"trad":"神態","simp":"神态","pinyin":"shen2 tai4","defs":["appearance","manner","bearing","deportment","look","expression","mien"]},{"trad":"神慰","simp":"神慰","pinyin":"shen2 wei4","defs":["spiritual consolation"]},{"trad":"神憎鬼厭","simp":"神憎鬼厌","pinyin":"shen2 zeng1 gui3 yan4","defs":["(idiom) despicable; loathsome"]},{"trad":"神戶","simp":"神户","pinyin":"Shen2 hu4","defs":["Kobe, city in Japan"]},{"trad":"神探","simp":"神探","pinyin":"shen2 tan4","defs":["master sleuth","lit. miraculous detective","cf Sherlock Holmes 福爾摩斯|福尔摩斯[Fu2 er3 mo2 si1] or Di Renjie 狄仁傑|狄仁杰[Di2 Ren2 jie2]"]},{"trad":"神明","simp":"神明","pinyin":"shen2 ming2","defs":["deities","gods"]},{"trad":"神智","simp":"神智","pinyin":"shen2 zhi4","defs":["mind","wisdom","consciousness"]},{"trad":"神曲","simp":"神曲","pinyin":"Shen2 qu3","defs":["The Divine Comedy by Dante Alighieri 但丁"]},{"trad":"神曲","simp":"神曲","pinyin":"shen2 qu1","defs":["medicated leaven (used in TCM to treat indigestion)"]},{"trad":"神枯","simp":"神枯","pinyin":"shen2 ku1","defs":["spiritual desolation"]},{"trad":"神格","simp":"神格","pinyin":"shen2 ge2","defs":["Godhead"]},{"trad":"神槍手","simp":"神枪手","pinyin":"shen2 qiang1 shou3","defs":["sharpshooter"]},{"trad":"神機妙算","simp":"神机妙算","pinyin":"shen2 ji1 miao4 suan4","defs":["divine strategy and wonderful planning (idiom)","clever scheme","supremely clever in his schemes"]},{"trad":"神權","simp":"神权","pinyin":"shen2 quan2","defs":["divine right (of kings)"]},{"trad":"神權政治","simp":"神权政治","pinyin":"shen2 quan2 zheng4 zhi4","defs":["theocracy"]},{"trad":"神權統治","simp":"神权统治","pinyin":"shen2 quan2 tong3 zhi4","defs":["theocracy"]},{"trad":"神殿","simp":"神殿","pinyin":"shen2 dian4","defs":["shrine"]},{"trad":"神氣","simp":"神气","pinyin":"shen2 qi4","defs":["expression","manner","vigorous","impressive","lofty","pretentious"]},{"trad":"神氣活現","simp":"神气活现","pinyin":"shen2 qi4 huo2 xian4","defs":["arrogant appearance","smug appearance","to act condescending","to put on airs"]},{"trad":"神池","simp":"神池","pinyin":"Shen2 chi2","defs":["Shenchi county in Xinzhou 忻州[Xin1 zhou1], Shanxi"]},{"trad":"神池縣","simp":"神池县","pinyin":"Shen2 chi2 xian4","defs":["Shenchi county in Xinzhou 忻州[Xin1 zhou1], Shanxi"]},{"trad":"神治","simp":"神治","pinyin":"shen2 zhi4","defs":["theocratic","theocracy"]},{"trad":"神治國","simp":"神治国","pinyin":"shen2 zhi4 guo2","defs":["theocracy","also written 神權統治|神权统治[shen2 quan2 tong3 zhi4] or 神權政治|神权政治[shen2 quan2 zheng4 zhi4]"]},{"trad":"神清氣爽","simp":"神清气爽","pinyin":"shen2 qing1 qi4 shuang3","defs":["(idiom) full of vitality","relaxed and alert"]},{"trad":"神游","simp":"神游","pinyin":"shen2 you2","defs":["to go on a mental journey"]},{"trad":"神漢","simp":"神汉","pinyin":"shen2 han4","defs":["sorcerer"]},{"trad":"神父","simp":"神父","pinyin":"shen2 fu5","defs":["father (Catholic or Orthodox priest)"]},{"trad":"神獸","simp":"神兽","pinyin":"shen2 shou4","defs":["mythological animal"]},{"trad":"神甫","simp":"神甫","pinyin":"shen2 fu5","defs":["variant of 神父[shen2 fu5]"]},{"trad":"神異","simp":"神异","pinyin":"shen2 yi4","defs":["magical","miraculous","mystical"]},{"trad":"神社","simp":"神社","pinyin":"shen2 she4","defs":["shrine"]},{"trad":"神祇","simp":"神祇","pinyin":"shen2 qi2","defs":["god","deity"]},{"trad":"神祕莫測","simp":"神秘莫测","pinyin":"shen2 mi4 mo4 ce4","defs":["mystery","unfathomable","enigmatic"]},{"trad":"神祖","simp":"神祖","pinyin":"shen2 zu3","defs":["Godhead"]},{"trad":"神神叨叨","simp":"神神叨叨","pinyin":"shen2 shen5 dao1 dao1","defs":["see 神神道道[shen2 shen5 dao4 dao4]"]},{"trad":"神神道道","simp":"神神道道","pinyin":"shen2 shen5 dao4 dao4","defs":["odd","weird","abnormal"]},{"trad":"神祠","simp":"神祠","pinyin":"shen2 ci2","defs":["shrine"]},{"trad":"神秘","simp":"神秘","pinyin":"shen2 mi4","defs":["mysterious","mystery"]},{"trad":"神秘主義","simp":"神秘主义","pinyin":"shen2 mi4 zhu3 yi4","defs":["mysticism"]},{"trad":"神秘面紗","simp":"神秘面纱","pinyin":"shen2 mi4 mian4 sha1","defs":["veil of mystery"]},{"trad":"神童","simp":"神童","pinyin":"shen2 tong2","defs":["child prodigy"]},{"trad":"神筆","simp":"神笔","pinyin":"shen2 bi3","defs":["lit. divine pen","fig. outstanding writing"]},{"trad":"神經","simp":"神经","pinyin":"shen2 jing1","defs":["nerve","mental state","(coll.) unhinged","nutjob"]},{"trad":"神經元","simp":"神经元","pinyin":"shen2 jing1 yuan2","defs":["neuron"]},{"trad":"神經元網","simp":"神经元网","pinyin":"shen2 jing1 yuan2 wang3","defs":["neural network"]},{"trad":"神經原","simp":"神经原","pinyin":"shen2 jing1 yuan2","defs":["variant of 神經元|神经元[shen2 jing1 yuan2]"]},{"trad":"神經原纖維","simp":"神经原纤维","pinyin":"shen2 jing1 yuan2 xian1 wei2","defs":["(anatomy) neurofibril"]},{"trad":"神經外科","simp":"神经外科","pinyin":"shen2 jing1 wai4 ke1","defs":["neurosurgery"]},{"trad":"神經大條","simp":"神经大条","pinyin":"shen2 jing1 da4 tiao2","defs":["thick-skinned","insensitive"]},{"trad":"神經失常","simp":"神经失常","pinyin":"shen2 jing1 shi1 chang2","defs":["mental aberration","nervous abnormality"]},{"trad":"神經學","simp":"神经学","pinyin":"shen2 jing1 xue2","defs":["neurology"]},{"trad":"神經學家","simp":"神经学家","pinyin":"shen2 jing1 xue2 jia1","defs":["neurologist"]},{"trad":"神經官能症","simp":"神经官能症","pinyin":"shen2 jing1 guan1 neng2 zheng4","defs":["neurosis"]},{"trad":"神經性","simp":"神经性","pinyin":"shen2 jing1 xing4","defs":["neural","mental","neurological"]},{"trad":"神經性毒劑","simp":"神经性毒剂","pinyin":"shen2 jing1 xing4 du2 ji4","defs":["nerve agent","nerve gas"]},{"trad":"神經毒素","simp":"神经毒素","pinyin":"shen2 jing1 du2 su4","defs":["neurotoxin"]},{"trad":"神經氨酸酶","simp":"神经氨酸酶","pinyin":"shen2 jing1 an1 suan1 mei2","defs":["neuraminidase (the N of virus such as bird flu H5N1)"]},{"trad":"神經生物學","simp":"神经生物学","pinyin":"shen2 jing1 sheng1 wu4 xue2","defs":["neurobiology"]},{"trad":"神經病","simp":"神经病","pinyin":"shen2 jing1 bing4","defs":["mental disorder","neuropathy","(derog.) mental case"]},{"trad":"神經症","simp":"神经症","pinyin":"shen2 jing1 zheng4","defs":["neurosis"]},{"trad":"神經痛","simp":"神经痛","pinyin":"shen2 jing1 tong4","defs":["neuralgia (medicine)"]},{"trad":"神經科","simp":"神经科","pinyin":"shen2 jing1 ke1","defs":["neurology department"]},{"trad":"神經突","simp":"神经突","pinyin":"shen2 jing1 tu1","defs":["nerve process"]},{"trad":"神經管","simp":"神经管","pinyin":"shen2 jing1 guan3","defs":["neural tube (embryology)"]},{"trad":"神經節","simp":"神经节","pinyin":"shen2 jing1 jie2","defs":["(anatomy) ganglion"]},{"trad":"神經系統","simp":"神经系统","pinyin":"shen2 jing1 xi4 tong3","defs":["nervous system"]},{"trad":"神經索","simp":"神经索","pinyin":"shen2 jing1 suo3","defs":["nerve cord"]},{"trad":"神經細胞","simp":"神经细胞","pinyin":"shen2 jing1 xi4 bao1","defs":["nerve cell; neuron"]},{"trad":"神經網","simp":"神经网","pinyin":"shen2 jing1 wang3","defs":["neural net"]},{"trad":"神經網絡","simp":"神经网络","pinyin":"shen2 jing1 wang3 luo4","defs":["neural network"]},{"trad":"神經網路","simp":"神经网路","pinyin":"shen2 jing1 wang3 lu4","defs":["neural network (artificial or biological)"]},{"trad":"神經纖維","simp":"神经纤维","pinyin":"shen2 jing1 xian1 wei2","defs":["(anatomy) nerve fiber"]},{"trad":"神經纖維瘤","simp":"神经纤维瘤","pinyin":"shen2 jing1 xian1 wei2 liu2","defs":["(medicine) neurofibroma"]},{"trad":"神經膠質","simp":"神经胶质","pinyin":"shen2 jing1 jiao1 zhi4","defs":["glial cell","neuroglia"]},{"trad":"神經膠質細胞","simp":"神经胶质细胞","pinyin":"shen2 jing1 jiao1 zhi4 xi4 bao1","defs":["glial cell (provide support to neuron)","neuroglia"]},{"trad":"神經衰弱","simp":"神经衰弱","pinyin":"shen2 jing1 shuai1 ruo4","defs":["nervous exhaustion; neurasthenia; mental breakdown (often used to describe what is now understood to be clinical depression)"]},{"trad":"神經質","simp":"神经质","pinyin":"shen2 jing1 zhi4","defs":["nervous","on edge","excitable","neurotic"]},{"trad":"神經過敏","simp":"神经过敏","pinyin":"shen2 jing1 guo4 min3","defs":["jumpy","nervous","oversensitive"]},{"trad":"神聖","simp":"神圣","pinyin":"shen2 sheng4","defs":["divine","hallow","holy","sacred"]},{"trad":"神聖不可侵犯","simp":"神圣不可侵犯","pinyin":"shen2 sheng4 bu4 ke3 qin1 fan4","defs":["sacred","inviolable"]},{"trad":"神聖羅馬帝國","simp":"神圣罗马帝国","pinyin":"Shen2 sheng4 Luo2 ma3 Di4 guo2","defs":["the Holy Roman Empire (history)"]},{"trad":"神聖週","simp":"神圣周","pinyin":"shen2 sheng4 zhou1","defs":["Holy week","Easter week (esp. Catholic)"]},{"trad":"神職","simp":"神职","pinyin":"shen2 zhi2","defs":["clergy","clerical"]},{"trad":"神職人員","simp":"神职人员","pinyin":"shen2 zhi2 ren2 yuan2","defs":["clergy","cleric"]},{"trad":"神舟","simp":"神舟","pinyin":"Shen2 zhou1","defs":["Shenzhou (spacecraft)","Hasee (computer manufacturer)"]},{"trad":"神舟號飛船","simp":"神舟号飞船","pinyin":"Shen2 zhou1 hao4 fei1 chuan2","defs":["Shenzhou (spacecraft)"]},{"trad":"神色","simp":"神色","pinyin":"shen2 se4","defs":["expression","look"]},{"trad":"神話","simp":"神话","pinyin":"shen2 hua4","defs":["legend","fairy tale","myth","mythology"]},{"trad":"神話故事","simp":"神话故事","pinyin":"shen2 hua4 gu4 shi5","defs":["mythical story; myth"]},{"trad":"神諭","simp":"神谕","pinyin":"shen2 yu4","defs":["oracle"]},{"trad":"神譜","simp":"神谱","pinyin":"shen2 pu3","defs":["list of Gods and Immortals","pantheon"]},{"trad":"神跡","simp":"神迹","pinyin":"shen2 ji4","defs":["miracle"]},{"trad":"神輿","simp":"神舆","pinyin":"shen2 yu2","defs":["mikoshi (Japanese portable Shinto shrine)"]},{"trad":"神農","simp":"神农","pinyin":"Shen2 nong2","defs":["Shennong or Farmer God (c. 2000 BC), first of the legendary Flame Emperors, 炎帝[Yan2 di4] and creator of agriculture"]},{"trad":"神農本草經","simp":"神农本草经","pinyin":"Shen2 nong2 Ben3 cao3 Jing1","defs":["Shennong's Compendium of Materia Medica, a Han dynasty pharmacological compendium, 3 scrolls"]},{"trad":"神農架","simp":"神农架","pinyin":"Shen2 nong2 jia4","defs":["Shennongjialin, directly administered forestry reserve in east Hubei"]},{"trad":"神農架地區","simp":"神农架地区","pinyin":"Shen2 nong2 jia4 di4 qu1","defs":["Shennongjialin, directly administered forestry reserve in east Hubei"]},{"trad":"神農架林區","simp":"神农架林区","pinyin":"Shen2 nong2 jia4 lin2 qu1","defs":["Shennongjialin, directly administered forestry reserve in east Hubei"]},{"trad":"神農氏","simp":"神农氏","pinyin":"Shen2 nong2 shi4","defs":["Shennong or Farmer God (c. 2000 BC), first of the legendary Flame Emperors, 炎帝[Yan2 di4] and creator of agriculture in China","followers or clan of Shennong 神農|神农[Shen2 nong2]"]},{"trad":"神通","simp":"神通","pinyin":"shen2 tong1","defs":["remarkable ability","magical power"]},{"trad":"神通廣大","simp":"神通广大","pinyin":"shen2 tong1 guang3 da4","defs":["(idiom) to possess great magical power; to possess remarkable abilities"]},{"trad":"神速","simp":"神速","pinyin":"shen2 su4","defs":["lightning speed","amazingly rapid","incredible pace of development"]},{"trad":"神造論","simp":"神造论","pinyin":"shen2 zao4 lun4","defs":["creationism"]},{"trad":"神道","simp":"神道","pinyin":"Shen2 dao4","defs":["Shinto (Japanese religion)"]},{"trad":"神道教","simp":"神道教","pinyin":"Shen2 dao4 jiao4","defs":["Shinto"]},{"trad":"神采","simp":"神采","pinyin":"shen2 cai3","defs":["expression","spirit","vigor"]},{"trad":"神采奕奕","simp":"神采奕奕","pinyin":"shen2 cai3 yi4 yi4","defs":["in glowing spirits (idiom); bursting with life","radiating health and vigor"]},{"trad":"神采飛揚","simp":"神采飞扬","pinyin":"shen2 cai3 fei1 yang2","defs":["in high spirits (idiom); glowing with health and vigor"]},{"trad":"神隱","simp":"神隐","pinyin":"shen2 yin3","defs":["to be concealed by supernatural forces; to disappear mysteriously; (fig.) to be out of the public eye"]},{"trad":"神雕俠侶","simp":"神雕侠侣","pinyin":"Shen2 diao1 Xia2 lu:3","defs":["variant of 神鵰俠侶|神雕侠侣[Shen2 diao1 Xia2 lu:3]"]},{"trad":"神靈","simp":"神灵","pinyin":"shen2 ling2","defs":["god","spirit","demon","occult or supernatural entities in general"]},{"trad":"神韻","simp":"神韵","pinyin":"shen2 yun4","defs":["charm or grace (in poetry or art)"]},{"trad":"神風特攻隊","simp":"神风特攻队","pinyin":"Shen2 feng1 Te4 gong1 dui4","defs":["Kamikaze Unit (Japanese corps of suicide pilots in World War II)","kamikaze (vodka-based cocktail)"]},{"trad":"神風突擊隊","simp":"神风突击队","pinyin":"shen2 feng1 tu1 ji1 dui4","defs":["kamikaze unit (Japanese corps of suicide pilots in World War II)"]},{"trad":"神馬","simp":"神马","pinyin":"shen2 ma3","defs":["mythical horse","Internet slang for 什麼|什么[shen2 me5]"]},{"trad":"神髓","simp":"神髓","pinyin":"shen2 sui3","defs":["lit. spirit and marrow","the essential character"]},{"trad":"神體","simp":"神体","pinyin":"shen2 ti3","defs":["Godhead"]},{"trad":"神魂","simp":"神魂","pinyin":"shen2 hun2","defs":["mind","state of mind (often abnormal)"]},{"trad":"神魂顛倒","simp":"神魂颠倒","pinyin":"shen2 hun2 dian1 dao3","defs":["lit. spirit and soul upside down (idiom); infatuated and head over heels in love","fascinated","captivated"]},{"trad":"神魔小說","simp":"神魔小说","pinyin":"shen2 mo2 xiao3 shuo1","defs":["supernatural novel","novel of ghosts and goblins"]},{"trad":"神鳥","simp":"神鸟","pinyin":"shen2 niao3","defs":["supernatural bird"]},{"trad":"神鵰俠侶","simp":"神雕侠侣","pinyin":"Shen2 diao1 Xia2 lu:3","defs":["\"The Return of the Condor Heroes\" (1959-61 wuxia novel by Jin Yong 金庸[Jin1 Yong1])"]},{"trad":"神龍汽車","simp":"神龙汽车","pinyin":"Shen2 long2 Qi4 che1","defs":["Dongfeng Peugeot-Citroën (automobile company)"]},{"trad":"神龕","simp":"神龛","pinyin":"shen2 kan1","defs":["shrine; niche; household shrine"]}],"聯":[{"trad":"聯","simp":"联","pinyin":"lian2","defs":["(bound form) to ally oneself with; to unite; to combine; to join","(bound form) (poetry) antithetical couplet"]},{"trad":"聯係","simp":"联系","pinyin":"lian2 xi4","defs":["variant of 聯繫|联系[lian2 xi4]"]},{"trad":"聯俄","simp":"联俄","pinyin":"lian2 E2","defs":["alliance with Russia (e.g. of early Chinese communists)"]},{"trad":"聯保","simp":"联保","pinyin":"lian2 bao3","defs":["joint guarantee (finance, law)"]},{"trad":"聯動","simp":"联动","pinyin":"lian2 dong4","defs":["(of the parts of a machine) to move together","to act in coordination; to be coupled","linkage"]},{"trad":"聯合","simp":"联合","pinyin":"lian2 he2","defs":["to combine","to join","unite","alliance"]},{"trad":"聯合公報","simp":"联合公报","pinyin":"lian2 he2 gong1 bao4","defs":["joint announcement"]},{"trad":"聯合包裹服務公司","simp":"联合包裹服务公司","pinyin":"Lian2 he2 Bao1 guo3 Fu2 wu4 Gong1 si1","defs":["United Parcel Service (UPS)"]},{"trad":"聯合古大陸","simp":"联合古大陆","pinyin":"lian2 he2 gu3 da4 lu4","defs":["Pangea or Pangaea"]},{"trad":"聯合品牌","simp":"联合品牌","pinyin":"lian2 he2 pin3 pai2","defs":["to cobrand"]},{"trad":"聯合國","simp":"联合国","pinyin":"Lian2 he2 guo2","defs":["United Nations"]},{"trad":"聯合國兒童基金會","simp":"联合国儿童基金会","pinyin":"Lian2 he2 guo2 Er2 tong2 Ji1 jin1 hui4","defs":["United Nations Children's Fund","UNICEF"]},{"trad":"聯合國大會","simp":"联合国大会","pinyin":"Lian2 he2 guo2 Da4 hui4","defs":["United Nations General Assembly"]},{"trad":"聯合國安全理事會","simp":"联合国安全理事会","pinyin":"Lian2 he2 guo2 An1 quan2 Li3 shi4 hui4","defs":["United Nations Security Council"]},{"trad":"聯合國憲章","simp":"联合国宪章","pinyin":"Lian2 he2 guo2 xian4 zhang1","defs":["United Nations charter"]},{"trad":"聯合國教科文組織","simp":"联合国教科文组织","pinyin":"Lian2 he2 guo2 Jiao4 Ke1 Wen2 Zu3 zhi1","defs":["UNESCO, United Nations Educational, Scientific and Cultural Organization"]},{"trad":"聯合國氣候變化框架公約","simp":"联合国气候变化框架公约","pinyin":"Lian2 he2 guo2 Qi4 hou4 Bian4 hua4 Kuang4 jia4 Gong1 yue1","defs":["United Nations Framework Convention on Climate Change"]},{"trad":"聯合國海洋法公約","simp":"联合国海洋法公约","pinyin":"Lian2 he2 guo2 Hai3 yang2 fa3 Gong1 yue1","defs":["United Nations Convention on the Law of the Sea"]},{"trad":"聯合國環境規劃署","simp":"联合国环境规划署","pinyin":"Lian2 he2 guo2 Huan2 jing4 Gui1 hua4 shu3","defs":["United Nations Environment Program (UNEP)"]},{"trad":"聯合國秘書處","simp":"联合国秘书处","pinyin":"Lian2 he2 guo2 Mi4 shu1 chu4","defs":["United Nations Secretariat"]},{"trad":"聯合國糧農組織","simp":"联合国粮农组织","pinyin":"Lian2 he2 guo2 Liang2 nong2 Zu3 zhi1","defs":["Food and Agriculture Organization of the United Nations (FAO)"]},{"trad":"聯合國開發計劃署","simp":"联合国开发计划署","pinyin":"Lian2 he2 guo2 Kai1 fa1 Ji4 hua4 shu3","defs":["United Nations Development Program"]},{"trad":"聯合國難民事務高級專員辦事處","simp":"联合国难民事务高级专员办事处","pinyin":"Lian2 he2 guo2 Nan2 min2 Shi4 wu4 Gao1 ji2 Zhuan1 yuan2 Ban4 shi4 chu4","defs":["Office of the UN High Commissioner for Refugees (UNHCR)"]},{"trad":"聯合報","simp":"联合报","pinyin":"Lian2 he2 Bao4","defs":["United Daily News, Taiwan newspaper"]},{"trad":"聯合式合成詞","simp":"联合式合成词","pinyin":"lian2 he2 shi4 he2 cheng2 ci2","defs":["coordinative compound word"]},{"trad":"聯合技術公司","simp":"联合技术公司","pinyin":"Lian2 he2 Ji4 shu4 Gong1 si1","defs":["United Technologies Corporation"]},{"trad":"聯合收割機","simp":"联合收割机","pinyin":"lian2 he2 shou1 ge1 ji1","defs":["combine (i.e. combine harvester)"]},{"trad":"聯合政府","simp":"联合政府","pinyin":"lian2 he2 zheng4 fu3","defs":["coalition government"]},{"trad":"聯合會","simp":"联合会","pinyin":"lian2 he2 hui4","defs":["federation"]},{"trad":"聯合王國","simp":"联合王国","pinyin":"Lian2 he2 wang2 guo2","defs":["United Kingdom"]},{"trad":"聯合組織","simp":"联合组织","pinyin":"lian2 he2 zu3 zhi1","defs":["syndicate"]},{"trad":"聯合聲明","simp":"联合声明","pinyin":"lian2 he2 sheng1 ming2","defs":["joint declaration"]},{"trad":"聯合自強","simp":"联合自强","pinyin":"lian2 he2 zi4 qiang2","defs":["to combine together for self-improvement","joint movement for self-strengthening"]},{"trad":"聯合艦隊","simp":"联合舰队","pinyin":"lian2 he2 jian4 dui4","defs":["combined fleet"]},{"trad":"聯合軍演","simp":"联合军演","pinyin":"lian2 he2 jun1 yan3","defs":["joint military exercise"]},{"trad":"聯名","simp":"联名","pinyin":"lian2 ming2","defs":["jointly (signed, declared, sponsored)"]},{"trad":"聯大","simp":"联大","pinyin":"Lian2 Da4","defs":["abbr. for 聯合國大會|联合国大会[Lian2 he2 guo2 Da4 hui4], United Nations General Assembly","abbr. for 國立西南聯合大學|国立西南联合大学[Guo2 li4 Xi1 nan2 Lian2 he2 Da4 xue2], National Southwest Combined University"]},{"trad":"聯姻","simp":"联姻","pinyin":"lian2 yin1","defs":["related by marriage","to connect by marriage (families, work units)"]},{"trad":"聯宗","simp":"联宗","pinyin":"lian2 zong1","defs":["combined branches of a clan"]},{"trad":"聯席會議","simp":"联席会议","pinyin":"lian2 xi2 hui4 yi4","defs":["joint conference"]},{"trad":"聯席董事","simp":"联席董事","pinyin":"lian2 xi2 dong3 shi4","defs":["associate director"]},{"trad":"聯想","simp":"联想","pinyin":"Lian2 xiang3","defs":["Lenovo"]},{"trad":"聯想","simp":"联想","pinyin":"lian2 xiang3","defs":["to associate (cognitively)","to make an associative connection","mental association","word prediction and auto-complete functions of input method editing programs"]},{"trad":"聯想學習","simp":"联想学习","pinyin":"lian2 xiang3 xue2 xi2","defs":["associative learning"]},{"trad":"聯想起","simp":"联想起","pinyin":"lian2 xiang3 qi3","defs":["to associate","to think of"]},{"trad":"聯想集團","simp":"联想集团","pinyin":"Lian2 xiang3 Ji2 tuan2","defs":["Lenovo Group (PRC computer firm)"]},{"trad":"聯手","simp":"联手","pinyin":"lian2 shou3","defs":["lit. to join hands","to act together"]},{"trad":"聯接","simp":"联接","pinyin":"lian2 jie1","defs":["variant of 連接|连接[lian2 jie1]"]},{"trad":"聯播","simp":"联播","pinyin":"lian2 bo1","defs":["to broadcast over a network","(radio or TV) hookup","simulcast"]},{"trad":"聯星","simp":"联星","pinyin":"lian2 xing1","defs":["binary star"]},{"trad":"聯機","simp":"联机","pinyin":"lian2 ji1","defs":["online","network","to connect online","to connect an electronic device to another device"]},{"trad":"聯機分析處理","simp":"联机分析处理","pinyin":"lian2 ji1 fen1 xi1 chu3 li3","defs":["(computing) OLAP (online analytical processing)"]},{"trad":"聯機遊戲","simp":"联机游戏","pinyin":"lian2 ji1 you2 xi4","defs":["a network computer game"]},{"trad":"聯歡","simp":"联欢","pinyin":"lian2 huan1","defs":["to have a get-together","celebration","party"]},{"trad":"聯歡會","simp":"联欢会","pinyin":"lian2 huan1 hui4","defs":["social gathering; party"]},{"trad":"聯氨","simp":"联氨","pinyin":"lian2 an1","defs":["hydrazine"]},{"trad":"聯營","simp":"联营","pinyin":"lian2 ying2","defs":["joint venture","under joint management"]},{"trad":"聯產","simp":"联产","pinyin":"lian2 chan3","defs":["co-production","cooperative production"]},{"trad":"聯產到勞","simp":"联产到劳","pinyin":"lian2 chan3 dao4 lao2","defs":["to pay sb according to their productivity"]},{"trad":"聯產到戶","simp":"联产到户","pinyin":"lian2 chan3 dao4 hu4","defs":["household responsibility system, introduced in the early 1980s, under which each rural household could freely decide what to produce and how to sell, as long as it fulfilled its quota of products to the state"]},{"trad":"聯盟","simp":"联盟","pinyin":"lian2 meng2","defs":["alliance","union","coalition"]},{"trad":"聯盟號","simp":"联盟号","pinyin":"Lian2 meng2 Hao4","defs":["Soyuz (union), Russian spacecraft series"]},{"trad":"聯立方程式","simp":"联立方程式","pinyin":"lian2 li4 fang1 cheng2 shi4","defs":["(math.) simultaneous equations; system of equations"]},{"trad":"聯結","simp":"联结","pinyin":"lian2 jie2","defs":["to combine; to join; to link"]},{"trad":"聯結主義","simp":"联结主义","pinyin":"lian2 jie2 zhu3 yi4","defs":["connectionism"]},{"trad":"聯結車","simp":"联结车","pinyin":"lian2 jie2 che1","defs":["(Tw) 18-wheeler","big rig","semi-trailer"]},{"trad":"聯絡","simp":"联络","pinyin":"lian2 luo4","defs":["to get in touch with","to contact","to stay in contact (with)","liaison","(math.) connection"]},{"trad":"聯絡人","simp":"联络人","pinyin":"lian2 luo4 ren2","defs":["(Tw) contact person"]},{"trad":"聯絡官","simp":"联络官","pinyin":"lian2 luo4 guan1","defs":["liaison officer"]},{"trad":"聯絡簿","simp":"联络簿","pinyin":"lian2 luo4 bu4","defs":["contact book"]},{"trad":"聯網","simp":"联网","pinyin":"lian2 wang3","defs":["to connect (or be connected) to a network; to network"]},{"trad":"聯綴","simp":"联缀","pinyin":"lian2 zhui4","defs":["variant of 連綴|连缀[lian2 zhui4]"]},{"trad":"聯綿","simp":"联绵","pinyin":"lian2 mian2","defs":["variant of 連綿|连绵[lian2 mian2]"]},{"trad":"聯綿詞","simp":"联绵词","pinyin":"lian2 mian2 ci2","defs":["two-syllable word featuring alliteration or rhyme, such as 玲瓏|玲珑[ling2 long2]"]},{"trad":"聯繫","simp":"联系","pinyin":"lian2 xi4","defs":["connection","contact","relation","to get in touch with","to integrate","to link","to touch"]},{"trad":"聯繫人","simp":"联系人","pinyin":"lian2 xi4 ren2","defs":["contact person"]},{"trad":"聯繫方式","simp":"联系方式","pinyin":"lian2 xi4 fang1 shi4","defs":["contact details"]},{"trad":"聯署","simp":"联署","pinyin":"lian2 shu3","defs":["joint signatures (on a letter or declaration)"]},{"trad":"聯翩","simp":"联翩","pinyin":"lian2 pian1","defs":["(literary) to come in quick succession","wave after wave"]},{"trad":"聯考","simp":"联考","pinyin":"lian2 kao3","defs":["entrance examination"]},{"trad":"聯聘","simp":"联聘","pinyin":"lian2 pin4","defs":["(of multiple institutions, departments or organizations) to jointly recruit; to jointly appoint (sb)"]},{"trad":"聯航","simp":"联航","pinyin":"Lian2 hang2","defs":["China United Airlines, abbr. for 中國聯合航空|中国联合航空[Zhong1 guo2 Lian2 he2 Hang2 kong1]"]},{"trad":"聯號","simp":"联号","pinyin":"lian2 hao4","defs":["variant of 連號|连号[lian2 hao4]"]},{"trad":"聯袂","simp":"联袂","pinyin":"lian2 mei4","defs":["jointly","as a group","together"]},{"trad":"聯誦","simp":"联诵","pinyin":"lian2 song4","defs":["liaison (in phonetics) (loanword)"]},{"trad":"聯誼","simp":"联谊","pinyin":"lian2 yi4","defs":["friendship","fellowship"]},{"trad":"聯誼會","simp":"联谊会","pinyin":"lian2 yi4 hui4","defs":["association","club","society","party","get-together"]},{"trad":"聯調聯試","simp":"联调联试","pinyin":"lian2 tiao2 lian2 shi4","defs":["debugging and commissioning","testing (of a whole system)"]},{"trad":"聯貫","simp":"联贯","pinyin":"lian2 guan4","defs":["variant of 連貫|连贯[lian2 guan4]"]},{"trad":"聯賽","simp":"联赛","pinyin":"lian2 sai4","defs":["(sports) league","league tournament"]},{"trad":"聯軍","simp":"联军","pinyin":"lian2 jun1","defs":["allied armies"]},{"trad":"聯軸器","simp":"联轴器","pinyin":"lian2 zhou4 qi4","defs":["(mechanics) coupler; coupling"]},{"trad":"聯軸節","simp":"联轴节","pinyin":"lian2 zhou4 jie2","defs":["(mechanics) coupling"]},{"trad":"聯通","simp":"联通","pinyin":"Lian2 tong1","defs":["China United Telecommunications Corporation","aka China Unicom or Unicom","abbr. for 中國聯通|中国联通"]},{"trad":"聯通","simp":"联通","pinyin":"lian2 tong1","defs":["connection","link","to link together"]},{"trad":"聯通紅籌公司","simp":"联通红筹公司","pinyin":"Lian2 tong1 Hong2 chou2 Gong1 si1","defs":["Unicom Red Chip, Hong Kong subsidiary of China Unicom 中國聯通|中国联通[Zhong1 guo2 Lian2 tong1]"]},{"trad":"聯運","simp":"联运","pinyin":"lian2 yun4","defs":["through transport","through traffic jointly organized by different enterprises"]},{"trad":"聯運票","simp":"联运票","pinyin":"lian2 yun4 piao4","defs":["transfer ticket"]},{"trad":"聯邦","simp":"联邦","pinyin":"lian2 bang1","defs":["federal","federation","commonwealth","federal union","federal state","union"]},{"trad":"聯邦制","simp":"联邦制","pinyin":"lian2 bang1 zhi4","defs":["federal","federal system"]},{"trad":"聯邦州","simp":"联邦州","pinyin":"lian2 bang1 zhou1","defs":["federal state","German Bundesland"]},{"trad":"聯邦德國","simp":"联邦德国","pinyin":"Lian2 bang1 De2 guo2","defs":["German Federation","Bundesrepublik Deutschland","Germany"]},{"trad":"聯邦快遞","simp":"联邦快递","pinyin":"Lian2 bang1 Kuai4 di4","defs":["FedEx"]},{"trad":"聯邦政府","simp":"联邦政府","pinyin":"lian2 bang1 zheng4 fu3","defs":["federal government"]},{"trad":"聯邦緊急措施署","simp":"联邦紧急措施署","pinyin":"Lian2 bang1 Jin3 ji2 Cuo4 shi1 shu3","defs":["Federal Emergency Management Agency (FEMA)"]},{"trad":"聯邦調查局","simp":"联邦调查局","pinyin":"Lian2 bang1 Diao4 cha2 ju2","defs":["Federal Bureau of Investigation (FBI)"]},{"trad":"聯邦通信委員會","simp":"联邦通信委员会","pinyin":"Lian2 bang1 Tong1 xin4 Wei3 yuan2 hui4","defs":["Federal Communications Commission (FCC)"]},{"trad":"聯隊","simp":"联队","pinyin":"lian2 dui4","defs":["wing (of an air force)","sports team representing a combination of entities (e.g. United Korea)"]},{"trad":"聯集","simp":"联集","pinyin":"lian2 ji2","defs":["union (symbol ∪) (set theory) (Tw)"]},{"trad":"聯體別墅","simp":"联体别墅","pinyin":"lian2 ti3 bie2 shu4","defs":["townhouse"]}],"舁":[{"trad":"舁","simp":"舁","pinyin":"yu2","defs":["to lift","to raise"]}],"苊":[{"trad":"苊","simp":"苊","pinyin":"e4","defs":["acenaphthene (C12H10)"]}],"莓":[{"trad":"莓","simp":"莓","pinyin":"mei2","defs":["berry","strawberry"]}],"葜":[{"trad":"葜","simp":"葜","pinyin":"qia1","defs":["used in 菝葜[ba2 qia1]"]}],"蔥":[{"trad":"蔥","simp":"葱","pinyin":"cong1","defs":["scallion","green onion"]},{"trad":"蔥屬","simp":"葱属","pinyin":"cong1 shu3","defs":["genus Allium"]},{"trad":"蔥嶺","simp":"葱岭","pinyin":"Cong1 ling3","defs":["old name for the Pamirs 帕米爾高原|帕米尔高原[Pa4 mi3 er3 Gao1 yuan2]"]},{"trad":"蔥抓餅","simp":"葱抓饼","pinyin":"cong1 zhua1 bing3","defs":["flaky scallion pancake (made with dough, not batter)"]},{"trad":"蔥油餅","simp":"葱油饼","pinyin":"cong1 you2 bing3","defs":["scallion pancake"]},{"trad":"蔥白","simp":"葱白","pinyin":"cong1 bai2","defs":["the white part of a green onion or scallion"]},{"trad":"蔥綠","simp":"葱绿","pinyin":"cong1 lu:4","defs":["verdant"]},{"trad":"蔥翠","simp":"葱翠","pinyin":"cong1 cui4","defs":["fresh green"]},{"trad":"蔥花","simp":"葱花","pinyin":"cong1 hua1","defs":["chopped green onions"]},{"trad":"蔥蔥","simp":"葱葱","pinyin":"cong1 cong1","defs":["verdant and thick (foliage, grass etc)"]},{"trad":"蔥蘢","simp":"葱茏","pinyin":"cong1 long2","defs":["verdant and lush"]},{"trad":"蔥頭","simp":"葱头","pinyin":"cong1 tou2","defs":["onion"]},{"trad":"蔥鬱","simp":"葱郁","pinyin":"cong1 yu4","defs":["verdant","lush green and full of life"]},{"trad":"蔥黃","simp":"葱黄","pinyin":"cong1 huang2","defs":["yellow green"]}],"衉":[{"trad":"衉","simp":"衉","pinyin":"ke4","defs":["to vomit"]}],"褒":[{"trad":"褒","simp":"褒","pinyin":"bao1","defs":["to praise","to commend","to honor","(of clothes) large or loose"]},{"trad":"褒呔","simp":"褒呔","pinyin":"bao1 tai1","defs":["bow tie (loanword) (Cantonese)"]},{"trad":"褒姒","simp":"褒姒","pinyin":"Bao1 si4","defs":["Baosi, concubine of King You of Zhou 周幽王[Zhou1 You1 wang2] and one of the famous Chinese beauties"]},{"trad":"褒忠","simp":"褒忠","pinyin":"Bao1 zhong1","defs":["Baozhong or Paochung township in Yunlin county 雲林縣|云林县[Yun2 lin2 xian4], Taiwan"]},{"trad":"褒忠鄉","simp":"褒忠乡","pinyin":"Bao1 zhong1 xiang1","defs":["Baozhong or Paochung township in Yunlin county 雲林縣|云林县[Yun2 lin2 xian4], Taiwan"]},{"trad":"褒揚","simp":"褒扬","pinyin":"bao1 yang2","defs":["to praise"]},{"trad":"褒禪山","simp":"褒禅山","pinyin":"Bao1 chan2 Shan1","defs":["Mt Baochan in Anhui","formerly known as Mt Hua 華山|华山"]},{"trad":"褒義","simp":"褒义","pinyin":"bao1 yi4","defs":["commendatory sense","positive connotation"]},{"trad":"褒貶","simp":"褒贬","pinyin":"bao1 bian3","defs":["to appraise","to pass judgment on","to speak ill of","praise and censure","appraisal"]}],"誤":[{"trad":"誤","simp":"误","pinyin":"wu4","defs":["mistake","error","to miss","to harm","to delay","to neglect","mistakenly"]},{"trad":"誤上賊船","simp":"误上贼船","pinyin":"wu4 shang4 zei2 chuan2","defs":["lit. to mistakenly board a pirate ship","to embark on a hopeless adventure"]},{"trad":"誤事","simp":"误事","pinyin":"wu4 shi4","defs":["to hold things up","to make a botch of things"]},{"trad":"誤人子弟","simp":"误人子弟","pinyin":"wu4 ren2 zi3 di4","defs":["(of a lazy or incompetent teacher) to hamper students' progress","(of media) to propagate errors","to lead people astray"]},{"trad":"誤作","simp":"误作","pinyin":"wu4 zuo4","defs":["to consider erroneously","incorrectly attributed to sb"]},{"trad":"誤信","simp":"误信","pinyin":"wu4 xin4","defs":["to falsely believe","to be mislead","to fall for (a trick etc)"]},{"trad":"誤傷","simp":"误伤","pinyin":"wu4 shang1","defs":["to injure accidentally","accidental injury"]},{"trad":"誤入歧途","simp":"误入歧途","pinyin":"wu4 ru4 qi2 tu2","defs":["to take a wrong step in life (idiom)","to go astray"]},{"trad":"誤判","simp":"误判","pinyin":"wu4 pan4","defs":["to misjudge","error of judgment","incorrect ruling","miscarriage of justice"]},{"trad":"誤判案","simp":"误判案","pinyin":"wu4 pan4 an4","defs":["miscarriage of justice"]},{"trad":"誤區","simp":"误区","pinyin":"wu4 qu1","defs":["mistaken ideas; misconceptions; the error of one's ways"]},{"trad":"誤寫","simp":"误写","pinyin":"wu4 xie3","defs":["to unwittingly write the wrong thing"]},{"trad":"誤導","simp":"误导","pinyin":"wu4 dao3","defs":["to mislead","to misguide","misleading"]},{"trad":"誤工","simp":"误工","pinyin":"wu4 gong1","defs":["to be late for or absent from work","to disrupt one's work; to cause a holdup in the work","loss of working time; a holdup"]},{"trad":"誤差","simp":"误差","pinyin":"wu4 cha1","defs":["difference","error","inaccuracy"]},{"trad":"誤打誤撞","simp":"误打误撞","pinyin":"wu4 da3 wu4 zhuang4","defs":["accidentally","to act before thinking"]},{"trad":"誤會","simp":"误会","pinyin":"wu4 hui4","defs":["to misunderstand","to mistake","misunderstanding","CL:個|个[ge4]"]},{"trad":"誤植","simp":"误植","pinyin":"wu4 zhi2","defs":["to write a word incorrectly","typo","(medicine) to mistakenly transplant (an infected organ etc)"]},{"trad":"誤機","simp":"误机","pinyin":"wu4 ji1","defs":["to miss a plane"]},{"trad":"誤殺","simp":"误杀","pinyin":"wu4 sha1","defs":["to mistakenly kill","manslaughter"]},{"trad":"誤用","simp":"误用","pinyin":"wu4 yong4","defs":["to misuse"]},{"trad":"誤繕","simp":"误缮","pinyin":"wu4 shan4","defs":["to miswrite (while copying written material); to transcribe incorrectly; to make a clerical error"]},{"trad":"誤置","simp":"误置","pinyin":"wu4 zhi4","defs":["to put sth in the wrong place"]},{"trad":"誤解","simp":"误解","pinyin":"wu4 jie3","defs":["to misunderstand","misunderstanding"]},{"trad":"誤診","simp":"误诊","pinyin":"wu4 zhen3","defs":["to misdiagnose","to be late in giving medical treatment"]},{"trad":"誤讀","simp":"误读","pinyin":"wu4 du2","defs":["to misread","(fig.) to misunderstand","to misinterpret"]},{"trad":"誤車","simp":"误车","pinyin":"wu4 che1","defs":["to miss (bus, train etc)"]},{"trad":"誤食","simp":"误食","pinyin":"wu4 shi2","defs":["to accidentally eat; to inadvertently ingest"]},{"trad":"誤點","simp":"误点","pinyin":"wu4 dian3","defs":["not on time","late (public transport, airlines)","overdue","behind schedule","delayed"]}],"譭":[{"trad":"譭","simp":"毁","pinyin":"hui3","defs":["variant of 毀|毁[hui3]","to defame","to slander"]}],"躑":[{"trad":"躑","simp":"踯","pinyin":"zhi2","defs":["used in 躑躅|踯躅[zhi2 zhu2]"]},{"trad":"躑躅","simp":"踯躅","pinyin":"zhi2 zhu2","defs":["(literary) to pace back and forth"]}],"連":[{"trad":"連","simp":"连","pinyin":"Lian2","defs":["surname Lian"]},{"trad":"連","simp":"连","pinyin":"lian2","defs":["to link","to join","to connect","continuously","in succession","including","(used with 也[ye3], 都[dou1] etc) even","company (military)"]},{"trad":"連三併四","simp":"连三并四","pinyin":"lian2 san1 bing4 si4","defs":["one after the other","in succession (idiom)"]},{"trad":"連中三元","simp":"连中三元","pinyin":"lian2 zhong4 san1 yuan2","defs":["(old) to rank first in the imperial examinations at the provincial capital, the national capital and the palace successively","(sports etc) to achieve three successes in a row (three matches in a row, three goals in a match etc)"]},{"trad":"連串","simp":"连串","pinyin":"lian2 chuan4","defs":["one after the other","a succession of","a series of"]},{"trad":"連任","simp":"连任","pinyin":"lian2 ren4","defs":["to continue in (a political) office","to serve for another term of office"]},{"trad":"連動","simp":"连动","pinyin":"lian2 dong4","defs":["to link","to peg (currency)","gang (gears)","continuously","serial verb construction"]},{"trad":"連動債","simp":"连动债","pinyin":"lian2 dong4 zhai4","defs":["structured note (finance)"]},{"trad":"連南","simp":"连南","pinyin":"Lian2 nan2","defs":["see 連南瑤族自治縣|连南瑶族自治县[Lian2 nan2 Yao2 zu2 Zi4 zhi4 xian4]"]},{"trad":"連南瑤族自治縣","simp":"连南瑶族自治县","pinyin":"Lian2 nan2 Yao2 zu2 Zi4 zhi4 xian4","defs":["Liannan Yao Autonomous County, in Qingyuan City 清遠市|清远市[Qing1 yuan3 Shi4], Guangdong"]},{"trad":"連南縣","simp":"连南县","pinyin":"Lian2 nan2 Xian4","defs":["see 連南瑤族自治縣|连南瑶族自治县[Lian2 nan2 Yao2 zu2 Zi4 zhi4 xian4]"]},{"trad":"連合","simp":"连合","pinyin":"lian2 he2","defs":["to combine","to join","to unite","alliance","same as 聯合|联合"]},{"trad":"連同","simp":"连同","pinyin":"lian2 tong2","defs":["together with","along with"]},{"trad":"連哄帶騙","simp":"连哄带骗","pinyin":"lian2 hong3 dai4 pian4","defs":["to cajole","to sweet talk sb into doing sth"]},{"trad":"連坐","simp":"连坐","pinyin":"lian2 zuo4","defs":["to treat as guilty those associated with an offender (family, neighbors etc)"]},{"trad":"連坐制","simp":"连坐制","pinyin":"lian2 zuo4 zhi4","defs":["guilt by association"]},{"trad":"連城","simp":"连城","pinyin":"Lian2 cheng2","defs":["see 連城縣|连城县[Lian2 cheng2 Xian4]"]},{"trad":"連城縣","simp":"连城县","pinyin":"Lian2 cheng2 Xian4","defs":["Liancheng, a county in Longyan City 龍巖市|龙岩市[Long2 yan2 Shi4], Fujian"]},{"trad":"連夜","simp":"连夜","pinyin":"lian2 ye4","defs":["that very night","through the night","for several nights in a row"]},{"trad":"連天","simp":"连天","pinyin":"lian2 tian1","defs":["reaching the sky","for days on end","incessantly"]},{"trad":"連奔帶跑","simp":"连奔带跑","pinyin":"lian2 ben1 dai4 pao3","defs":["to run quickly","to rush","to gallop"]},{"trad":"連字符","simp":"连字符","pinyin":"lian2 zi4 fu2","defs":["hyphen"]},{"trad":"連字符號","simp":"连字符号","pinyin":"lian2 zi4 fu2 hao4","defs":["hyphen"]},{"trad":"連字號","simp":"连字号","pinyin":"lian2 zi4 hao4","defs":["hyphen (punct.)"]},{"trad":"連宵","simp":"连宵","pinyin":"lian2 xiao1","defs":["the same night","that very night","successive nights"]},{"trad":"連寫","simp":"连写","pinyin":"lian2 xie3","defs":["to write without lifting one's pen from the paper","(in the Romanization of Chinese) to write two or more syllables together as a single word (not separated by spaces)"]},{"trad":"連山","simp":"连山","pinyin":"Lian2 shan1","defs":["see 連山壯族瑤族自治縣|连山壮族瑶族自治县[Lian2 shan1 Zhuang4 zu2 Yao2 zu2 Zi4 zhi4 xian4]","see 連山區|连山区[Lian2 shan1 Qu1]"]},{"trad":"連山區","simp":"连山区","pinyin":"Lian2 shan1 qu1","defs":["Lianshan district of Huludao city 葫蘆島市|葫芦岛市, Liaoning"]},{"trad":"連山壯族瑤族自治縣","simp":"连山壮族瑶族自治县","pinyin":"Lian2 shan1 Zhuang4 zu2 Yao2 zu2 Zi4 zhi4 xian4","defs":["Lianshan Zhuang and Yao Autonomous County, in Qingyuan City 清遠市|清远市[Qing1 yuan3 Shi4], Guangdong"]},{"trad":"連山縣","simp":"连山县","pinyin":"Lian2 shan1 Xian4","defs":["see 連山壯族瑤族自治縣|连山壮族瑶族自治县[Lian2 shan1 Zhuang4 zu2 Yao2 zu2 Zi4 zhi4 xian4]"]},{"trad":"連州","simp":"连州","pinyin":"Lian2 zhou1","defs":["see 連州市|连州市[Lian2 zhou1 Shi4]"]},{"trad":"連州市","simp":"连州市","pinyin":"Lian2 zhou1 Shi4","defs":["Lianzhou, a county-level city in Qingyuan City 清遠市|清远市[Qing1 yuan3 Shi4], Guangdong"]},{"trad":"連巹","simp":"连卺","pinyin":"lian2 jin3","defs":["to share nuptial cup","(fig.) to get married"]},{"trad":"連帶","simp":"连带","pinyin":"lian2 dai4","defs":["to be related","to entail","to involve","joint (liability etc)"]},{"trad":"連帶責任","simp":"连带责任","pinyin":"lian2 dai4 ze2 ren4","defs":["to bear joint responsibility for sth","joint liability (law)"]},{"trad":"連帽衛衣","simp":"连帽卫衣","pinyin":"lian2 mao4 wei4 yi1","defs":["hooded sweatshirt","hoodie"]},{"trad":"連平","simp":"连平","pinyin":"Lian2 ping2","defs":["see 連平縣|连平县[Lian2 ping2 Xian4]"]},{"trad":"連平縣","simp":"连平县","pinyin":"Lian2 ping2 Xian4","defs":["Lianping, a county in Heyuan City 河源市[He2 yuan2 Shi4], Guangdong"]},{"trad":"連年","simp":"连年","pinyin":"lian2 nian2","defs":["successive years","over many years"]},{"trad":"連忙","simp":"连忙","pinyin":"lian2 mang2","defs":["promptly; at once"]},{"trad":"連戰","simp":"连战","pinyin":"Lian2 Zhan4","defs":["Lien Chan (1936-), Taiwanese politician, former vice-president and chairman of Guomintang"]},{"trad":"連戰連勝","simp":"连战连胜","pinyin":"lian2 zhan4 lian2 sheng4","defs":["fighting and winning a series of battles (idiom); ever victorious"]},{"trad":"連手","simp":"连手","pinyin":"lian2 shou3","defs":["concerted action","to collude (in dishonesty)"]},{"trad":"連拖帶拉","simp":"连拖带拉","pinyin":"lian2 tuo1 dai4 la1","defs":["pushing and pulling (idiom)"]},{"trad":"連招","simp":"连招","pinyin":"lian2 zhao1","defs":["(gaming or martial arts) a sequence of attacks or moves; combo"]},{"trad":"連指手套","simp":"连指手套","pinyin":"lian2 zhi3 shou3 tao4","defs":["mittens"]},{"trad":"連接","simp":"连接","pinyin":"lian2 jie1","defs":["to link; to join; to connect"]},{"trad":"連接器","simp":"连接器","pinyin":"lian2 jie1 qi4","defs":["connector"]},{"trad":"連接框","simp":"连接框","pinyin":"lian2 jie1 kuang4","defs":["connection frame","linked frame"]},{"trad":"連接至","simp":"连接至","pinyin":"lian2 jie1 zhi4","defs":["to connect to"]},{"trad":"連接號","simp":"连接号","pinyin":"lian2 jie1 hao4","defs":["hyphen"]},{"trad":"連接詞","simp":"连接词","pinyin":"lian2 jie1 ci2","defs":["conjunction"]},{"trad":"連接酶","simp":"连接酶","pinyin":"lian2 jie1 mei2","defs":["ligase"]},{"trad":"連擊","simp":"连击","pinyin":"lian2 ji1","defs":["to batter","combo (hit) (gaming)","(volleyball, table tennis etc) double hit","double contact"]},{"trad":"連敗","simp":"连败","pinyin":"lian2 bai4","defs":["consecutive defeats","to lose several times in a row"]},{"trad":"連日","simp":"连日","pinyin":"lian2 ri4","defs":["day after day","for several days running"]},{"trad":"連書","simp":"连书","pinyin":"lian2 shu1","defs":["to write without lifting one's pen from the paper","(in the Romanization of Chinese) to write two or more syllables together as a single word (not separated by spaces)"]},{"trad":"連本帶利","simp":"连本带利","pinyin":"lian2 ben3 dai4 li4","defs":["both principal and interest","capital plus profit"]},{"trad":"連枷","simp":"连枷","pinyin":"lian2 jia1","defs":["flail"]},{"trad":"連枷胸","simp":"连枷胸","pinyin":"lian2 jia1 xiong1","defs":["flail chest (medicine)"]},{"trad":"連根拔","simp":"连根拔","pinyin":"lian2 gen1 ba2","defs":["to pull up by the roots","to uproot"]},{"trad":"連橫","simp":"连横","pinyin":"Lian2 Heng2","defs":["Horizontal Alliance, clique of the School of Diplomacy 縱橫家|纵横家[Zong4 heng2 jia1] during the Warring States Period (425-221 BC)"]},{"trad":"連歌","simp":"连歌","pinyin":"lian2 ge1","defs":["renga"]},{"trad":"連比","simp":"连比","pinyin":"lian2 bi3","defs":["compound ratio"]},{"trad":"連江","simp":"连江","pinyin":"Lian2 jiang1","defs":["see 連江縣|连江县[Lian2 jiang1 Xian4]"]},{"trad":"連江縣","simp":"连江县","pinyin":"Lian2 jiang1 Xian4","defs":["Lianjiang, a county in Fuzhou City 福州市[Fu2 zhou1 Shi4], Fujian","Lienchiang County, the official name of the Matsu Islands 馬祖列島|马祖列岛[Ma3 zu3 Lie4 dao3], a county of the ROC (based in Taiwan)"]},{"trad":"連滾帶爬","simp":"连滚带爬","pinyin":"lian2 gun3 dai4 pa2","defs":["(idiom) stumbling and crawling; scrambling; frantically trying to escape"]},{"trad":"連片","simp":"连片","pinyin":"lian2 pian4","defs":["forming a continuous sheet","continuous","contiguous","closely grouped"]},{"trad":"連珠","simp":"连珠","pinyin":"lian2 zhu1","defs":["joined as a string of pearls","in rapid succession","alignment","Renju, a Japanese game, also called Gomoku or five-in-a-row"]},{"trad":"連珠砲","simp":"连珠炮","pinyin":"lian2 zhu1 pao4","defs":["barrage of gunfire (often used as a metaphor for rapid speech)"]},{"trad":"連理","simp":"连理","pinyin":"lian2 li3","defs":["two trees that grow together as one","fig. conjugal union"]},{"trad":"連璧","simp":"连璧","pinyin":"lian2 bi4","defs":["to join jade annuli","fig. to combine two good things"]},{"trad":"連環","simp":"连环","pinyin":"lian2 huan2","defs":["chain"]},{"trad":"連環圖","simp":"连环图","pinyin":"lian2 huan2 tu2","defs":["comic strip"]},{"trad":"連環殺手","simp":"连环杀手","pinyin":"lian2 huan2 sha1 shou3","defs":["serial killer"]},{"trad":"連環畫","simp":"连环画","pinyin":"lian2 huan2 hua4","defs":["lianhuanhua (graphic novel)"]},{"trad":"連環計","simp":"连环计","pinyin":"lian2 huan2 ji4","defs":["coordinated sequence of strategic moves"]},{"trad":"連用","simp":"连用","pinyin":"lian2 yong4","defs":["to use (two words etc) together","to use (sth) continuously"]},{"trad":"連番","simp":"连番","pinyin":"lian2 fan1","defs":["repeatedly"]},{"trad":"連發","simp":"连发","pinyin":"lian2 fa1","defs":["to fire (a weapon) in rapid succession"]},{"trad":"連筆","simp":"连笔","pinyin":"lian2 bi3","defs":["to write without lifting one's pen from the paper"]},{"trad":"連篇累牘","simp":"连篇累牍","pinyin":"lian2 pian1 lei3 du2","defs":["(of a piece of writing) long and tedious (idiom)","verbose"]},{"trad":"連累","simp":"连累","pinyin":"lian2 lei5","defs":["to implicate; to get (sb) into trouble","also pr. [lian2lei3] or [lian2lei4]"]},{"trad":"連結","simp":"连结","pinyin":"lian2 jie2","defs":["variant of 聯結|联结[lian2 jie2]","(Tw) link (on a website); hyperlink"]},{"trad":"連結主義","simp":"连结主义","pinyin":"lian2 jie2 zhu3 yi4","defs":["connectionism"]},{"trad":"連結線","simp":"连结线","pinyin":"lian2 jie2 xian4","defs":["tie (music)"]},{"trad":"連絡","simp":"连络","pinyin":"lian2 luo4","defs":["variant of 聯絡|联络[lian2 luo4]"]},{"trad":"連綴","simp":"连缀","pinyin":"lian2 zhui4","defs":["to put together","linking","successive","a cluster"]},{"trad":"連綴動詞","simp":"连缀动词","pinyin":"lian2 zhui4 dong4 ci2","defs":["linking verb"]},{"trad":"連綿","simp":"连绵","pinyin":"lian2 mian2","defs":["continuous","unbroken","uninterrupted","extending forever into the distance (of mountain range, river etc)"]},{"trad":"連綿不絕","simp":"连绵不绝","pinyin":"lian2 mian2 bu4 jue2","defs":["(idiom) continuous; unending"]},{"trad":"連綿詞","simp":"连绵词","pinyin":"lian2 mian2 ci2","defs":["variant of 聯綿詞|联绵词[lian2 mian2 ci2]"]},{"trad":"連線","simp":"连线","pinyin":"lian2 xian4","defs":["electrical lead; connecting line","(Tw) to connect (to a network, device etc); to go online; connection","(congressional) caucus"]},{"trad":"連縣","simp":"连县","pinyin":"Lian2 xian4","defs":["Lian county in Guangdong"]},{"trad":"連繫","simp":"连系","pinyin":"lian2 xi4","defs":["to link","to connect"]},{"trad":"連繫詞","simp":"连系词","pinyin":"lian2 xi4 ci2","defs":["copula (linguistics)"]},{"trad":"連續","simp":"连续","pinyin":"lian2 xu4","defs":["continuous","in a row","serial","consecutive"]},{"trad":"連續不斷","simp":"连续不断","pinyin":"lian2 xu4 bu4 duan4","defs":["continuous","unceasing"]},{"trad":"連續介質力學","simp":"连续介质力学","pinyin":"lian2 xu4 jie4 zhi4 li4 xue2","defs":["mechanics of a continuous medium","fluid mechanics"]},{"trad":"連續函數","simp":"连续函数","pinyin":"lian2 xu4 han2 shu4","defs":["continuous function"]},{"trad":"連續劇","simp":"连续剧","pinyin":"lian2 xu4 ju4","defs":["serialized drama","dramatic series","show in parts"]},{"trad":"連續性","simp":"连续性","pinyin":"lian2 xu4 xing4","defs":["continuity"]},{"trad":"連續犯","simp":"连续犯","pinyin":"lian2 xu4 fan4","defs":["successive offenses","serial crime"]},{"trad":"連續監視","simp":"连续监视","pinyin":"lian2 xu4 jian1 shi4","defs":["continuous monitoring"]},{"trad":"連續統假設","simp":"连续统假设","pinyin":"lian2 xu4 tong3 jia3 she4","defs":["(math.) the continuum hypothesis"]},{"trad":"連續變調","simp":"连续变调","pinyin":"lian2 xu4 bian4 diao4","defs":["tone sandhi"]},{"trad":"連續集","simp":"连续集","pinyin":"lian2 xu4 ji2","defs":["TV series"]},{"trad":"連續體","simp":"连续体","pinyin":"lian2 xu4 ti3","defs":["continuum"]},{"trad":"連署","simp":"连署","pinyin":"lian2 shu3","defs":["to cosign","to countersign"]},{"trad":"連翩","simp":"连翩","pinyin":"lian2 pian1","defs":["variant of 聯翩|联翩[lian2 pian1]"]},{"trad":"連翹","simp":"连翘","pinyin":"lian2 qiao2","defs":["Forsythia"]},{"trad":"連聲","simp":"连声","pinyin":"lian2 sheng1","defs":["repeatedly (say something)"]},{"trad":"連號","simp":"连号","pinyin":"lian2 hao4","defs":["consecutive serial numbers","chain (of supermarkets, hotels etc)","hyphen"]},{"trad":"連衣裙","simp":"连衣裙","pinyin":"lian2 yi1 qun2","defs":["a one-piece dress"]},{"trad":"連袂","simp":"连袂","pinyin":"lian2 mei4","defs":["variant of 聯袂|联袂[lian2 mei4]"]},{"trad":"連褲襪","simp":"连裤袜","pinyin":"lian2 ku4 wa4","defs":["pantyhose; tights","CL:雙|双[shuang1]"]},{"trad":"連襟","simp":"连襟","pinyin":"lian2 jin1","defs":["husbands of sisters","brothers-in-law","extremely close (of a relationship)"]},{"trad":"連詞","simp":"连词","pinyin":"lian2 ci2","defs":["conjunction"]},{"trad":"連讀","simp":"连读","pinyin":"lian2 du2","defs":["liaison (in phonetics)"]},{"trad":"連貫","simp":"连贯","pinyin":"lian2 guan4","defs":["to link up (disparate elements)","coherent (narrative, argument etc)"]},{"trad":"連踢帶打","simp":"连踢带打","pinyin":"lian2 ti1 dai4 da3","defs":["to kick and beat (idiom)"]},{"trad":"連軸轉","simp":"连轴转","pinyin":"lian2 zhou2 zhuan4","defs":["(coll.) to work non-stop; to work around the clock"]},{"trad":"連載","simp":"连载","pinyin":"lian2 zai3","defs":["serialized","published as a serial (in a newspaper)"]},{"trad":"連通","simp":"连通","pinyin":"lian2 tong1","defs":["to connect","to communicate","to relate","(math.) connected"]},{"trad":"連通器","simp":"连通器","pinyin":"lian2 tong1 qi4","defs":["communicating vessels (in scientific experiment)"]},{"trad":"連連","simp":"连连","pinyin":"lian2 lian2","defs":["repeatedly","again and again"]},{"trad":"連連看","simp":"连连看","pinyin":"lian2 lian2 kan4","defs":["pattern matching (puzzle game)","matching (type of test question in which presented items are to be paired up)"]},{"trad":"連銷店","simp":"连销店","pinyin":"lian2 xiao1 dian4","defs":["chain store"]},{"trad":"連鍋端","simp":"连锅端","pinyin":"lian2 guo1 duan1","defs":["to take even the cooking pots (idiom)","to clean out","to wipe out"]},{"trad":"連鎖","simp":"连锁","pinyin":"lian2 suo3","defs":["to interlock","to be linked","chain (store etc)"]},{"trad":"連鎖反應","simp":"连锁反应","pinyin":"lian2 suo3 fan3 ying4","defs":["(physics) chain reaction","(idiom) chain reaction; series of events each caused by the previous one"]},{"trad":"連鎖商店","simp":"连锁商店","pinyin":"lian2 suo3 shang1 dian4","defs":["chain store"]},{"trad":"連鎖店","simp":"连锁店","pinyin":"lian2 suo3 dian4","defs":["chain store"]},{"trad":"連鑄","simp":"连铸","pinyin":"lian2 zhu4","defs":["continuous casting (metallurgy)"]},{"trad":"連鑣並軫","simp":"连镳并轸","pinyin":"lian2 biao1 bing4 zhen3","defs":["lit. reins together and carriages level (idiom); keeping exactly abreast of one another","running neck and neck"]},{"trad":"連長","simp":"连长","pinyin":"lian2 zhang3","defs":["company commander"]},{"trad":"連陰雨","simp":"连阴雨","pinyin":"lian2 yin1 yu3","defs":["prolonged spell of rainy weather"]},{"trad":"連隊","simp":"连队","pinyin":"lian2 dui4","defs":["company (of troops)"]},{"trad":"連雲","simp":"连云","pinyin":"Lian2 yun2","defs":["see 連雲區|连云区[Lian2 yun2 Qu1]"]},{"trad":"連雲區","simp":"连云区","pinyin":"Lian2 yun2 Qu1","defs":["Lianyun, a district of Lianyungang City 連雲港市|连云港市[Lian2 yun2 gang3 Shi4], Jiangsu"]},{"trad":"連雲港","simp":"连云港","pinyin":"Lian2 yun2 gang3","defs":["see 連雲港市|连云港市[Lian2 yun2 gang3 Shi4]"]},{"trad":"連雲港市","simp":"连云港市","pinyin":"Lian2 yun2 gang3 Shi4","defs":["Lianyungang, prefecture-level city in Jiangsu Province 江蘇省|江苏省[Jiang1 su1 Sheng3]"]},{"trad":"連音","simp":"连音","pinyin":"lian2 yin1","defs":["tuplet (music)","sandhi (phonetics)"]},{"trad":"連音符","simp":"连音符","pinyin":"lian2 yin1 fu2","defs":["(music) tuplet"]},{"trad":"連骨肉","simp":"连骨肉","pinyin":"lian2 gu3 rou4","defs":["chop","rib meat"]},{"trad":"連體","simp":"连体","pinyin":"lian2 ti3","defs":["conjoined (twins)","one-piece (garment)"]},{"trad":"連體嬰","simp":"连体婴","pinyin":"lian2 ti3 ying1","defs":["conjoined twins"]},{"trad":"連體嬰兒","simp":"连体婴儿","pinyin":"lian2 ti3 ying1 er2","defs":["conjoined twins","Siamese twins"]},{"trad":"連體泳衣","simp":"连体泳衣","pinyin":"lian2 ti3 yong3 yi1","defs":["one-piece swimsuit"]},{"trad":"連體褲","simp":"连体裤","pinyin":"lian2 ti3 ku4","defs":["jumpsuit"]},{"trad":"連體雙胞胎","simp":"连体双胞胎","pinyin":"lian2 ti3 shuang1 bao1 tai1","defs":["conjoined twins","Siamese twins"]},{"trad":"連麥","simp":"连麦","pinyin":"lian2 mai4","defs":["(of two people in different locations) to sing or otherwise perform together using communications technology"]}],"醵":[{"trad":"醵","simp":"醵","pinyin":"ju4","defs":["to contribute to a feast","to pool (money)"]}],"鉾":[{"trad":"鉾","simp":"𫓴","pinyin":"mou2","defs":["(archaic) battle helmet (variant of 鍪[mou2])"]}],"鍇":[{"trad":"鍇","simp":"锴","pinyin":"kai3","defs":["high quality iron"]}],"鐐":[{"trad":"鐐","simp":"镣","pinyin":"liao4","defs":["fetters","leg-irons","shackles"]},{"trad":"鐐銬","simp":"镣铐","pinyin":"liao4 kao4","defs":["manacles and leg-irons","fetters and handcuffs"]},{"trad":"鐐鎖","simp":"镣锁","pinyin":"liao4 suo3","defs":["fetter lock (to restrain horse)","handcuff lock"]}],"関":[{"trad":"関","simp":"関","pinyin":"guan1","defs":["variant of 關|关[guan1]"]}],"飆":[{"trad":"飆","simp":"飙","pinyin":"biao1","defs":["(literary) very strong wind; gale","(bound form) wild; violent; unrestrained; furious"]},{"trad":"飆升","simp":"飙升","pinyin":"biao1 sheng1","defs":["to rise rapidly","to soar"]},{"trad":"飆口水","simp":"飙口水","pinyin":"biao1 kou3 shui3","defs":["gossip","idle chat"]},{"trad":"飆汗","simp":"飙汗","pinyin":"biao1 han4","defs":["to sweat profusely"]},{"trad":"飆漲","simp":"飙涨","pinyin":"biao1 zhang3","defs":["(of prices) to skyrocket; to soar"]},{"trad":"飆車","simp":"飙车","pinyin":"biao1 che1","defs":["to drive recklessly at high speed; street racing (motorbikes or cars)"]},{"trad":"飆風","simp":"飙风","pinyin":"biao1 feng1","defs":["fierce wind"]}],"驘":[{"trad":"驘","simp":"骡","pinyin":"luo2","defs":["variant of 騾|骡[luo2]"]}],"鯪":[{"trad":"鯪","simp":"鲮","pinyin":"ling2","defs":["mud carp (Cirrhina molitorella)"]},{"trad":"鯪魚","simp":"鲮鱼","pinyin":"ling2 yu2","defs":["see 鯪|鲮[ling2]"]},{"trad":"鯪鯉","simp":"鲮鲤","pinyin":"ling2 li3","defs":["pangolin (Manis pentadactylata)","scaly ant-eater"]},{"trad":"鯪鯉甲","simp":"鲮鲤甲","pinyin":"ling2 li3 jia3","defs":["pangolin (Manis pentadactylata)","scaly ant-eater"]},{"trad":"鯪鯉科","simp":"鲮鲤科","pinyin":"ling2 li3 ke1","defs":["the pangolin family"]}],"鼎":[{"trad":"鼎","simp":"鼎","pinyin":"ding3","defs":["ancient cooking cauldron with two looped handles and three or four legs","pot (dialect)","to enter upon a period of (classical)","Kangxi radical 206","one of the 64 hexagrams of the Book of Changes"]},{"trad":"鼎力","simp":"鼎力","pinyin":"ding3 li4","defs":["(honorific) your kind efforts","thanks to your help"]},{"trad":"鼎力相助","simp":"鼎力相助","pinyin":"ding3 li4 xiang1 zhu4","defs":["We are most grateful for your valuable assistance."]},{"trad":"鼎助","simp":"鼎助","pinyin":"ding3 zhu4","defs":["(honorific) your inestimable assistance","thanks to your help"]},{"trad":"鼎城","simp":"鼎城","pinyin":"Ding3 cheng2","defs":["see 鼎城區|鼎城区[Ding3 cheng2 Qu1]"]},{"trad":"鼎城區","simp":"鼎城区","pinyin":"Ding3 cheng2 Qu1","defs":["Dingcheng, a district of Changde City 常德市[Chang2 de2 Shi4], Hunan"]},{"trad":"鼎峙","simp":"鼎峙","pinyin":"ding3 zhi4","defs":["(literary) to form a tripartite confrontation"]},{"trad":"鼎新","simp":"鼎新","pinyin":"ding3 xin1","defs":["to innovate"]},{"trad":"鼎族","simp":"鼎族","pinyin":"ding3 zu2","defs":["rich patriarchal family","aristocracy"]},{"trad":"鼎沸","simp":"鼎沸","pinyin":"ding3 fei4","defs":["a confused noise","a racket"]},{"trad":"鼎泰豐","simp":"鼎泰丰","pinyin":"Ding3 tai4 feng1","defs":["Din Tai Fung, restaurant specializing in dumplings, with stores in many countries"]},{"trad":"鼎湖","simp":"鼎湖","pinyin":"Ding3 hu2","defs":["see 鼎湖區|鼎湖区[Ding3 hu2 Qu1]"]},{"trad":"鼎湖區","simp":"鼎湖区","pinyin":"Ding3 hu2 Qu1","defs":["Dinghu, a district of Zhaoqing City 肇慶市|肇庆市[Zhao4 qing4 Shi4], Guangdong"]},{"trad":"鼎盛","simp":"鼎盛","pinyin":"ding3 sheng4","defs":["thriving","flourishing"]},{"trad":"鼎盛時期","simp":"鼎盛时期","pinyin":"ding3 sheng4 shi2 qi1","defs":["flourishing period","golden age"]},{"trad":"鼎盛期","simp":"鼎盛期","pinyin":"ding3 sheng4 qi1","defs":["golden age; heyday; period of peak prosperity"]},{"trad":"鼎立","simp":"鼎立","pinyin":"ding3 li4","defs":["lit. to stand like the three legs of a tripod","tripartite confrontation or balance of forces"]},{"trad":"鼎足","simp":"鼎足","pinyin":"ding3 zu2","defs":["lit. the three legs of a tripod","fig. three competing rivals"]},{"trad":"鼎足之勢","simp":"鼎足之势","pinyin":"ding3 zu2 zhi1 shi4","defs":["competition between three rivals","tripartite confrontation"]},{"trad":"鼎鐺玉石","simp":"鼎铛玉石","pinyin":"ding3 cheng1 yu4 shi2","defs":["lit. to use a sacred tripod as cooking pot and jade as ordinary stone (idiom); fig. a waste of precious material","casting pearls before swine"]},{"trad":"鼎革","simp":"鼎革","pinyin":"ding3 ge2","defs":["change of dynasties","clear out the old, bring in the new"]},{"trad":"鼎食","simp":"鼎食","pinyin":"ding3 shi2","defs":["extravagant food"]},{"trad":"鼎鼎","simp":"鼎鼎","pinyin":"ding3 ding3","defs":["great","very important"]},{"trad":"鼎鼎大名","simp":"鼎鼎大名","pinyin":"ding3 ding3 da4 ming2","defs":["famous","celebrated"]}]}