[{"trad":"UP主","simp":"UP主","pinyin":"U P zhu3","defs":["(Internet slang) uploader (person who uploads a video or other content to the Internet)","pronounced [a4 pu5 zhu3]","(loanword from Japanese うｐ主, \"upunushi\")"]},{"trad":"USB手指","simp":"USB手指","pinyin":"U S B shou3 zhi3","defs":["USB flash drive"]},{"trad":"U凸內褲","simp":"U凸内裤","pinyin":"U tu1 nei4 ku4","defs":["contour pouch brief (men's underwear)"]},{"trad":"U型枕","simp":"U型枕","pinyin":"U xing2 zhen3","defs":["travel pillow"]},{"trad":"U型池","simp":"U型池","pinyin":"U xing2 chi2","defs":["(sports) vert ramp; half-pipe"]},{"trad":"U形轉彎","simp":"U形转弯","pinyin":"U xing2 zhuan3 wan1","defs":["U-turn"]},{"trad":"U盤","simp":"U盘","pinyin":"U pan2","defs":["USB flash drive; thumb drive"]},{"trad":"U盾","simp":"U盾","pinyin":"U dun4","defs":["USB key used as a security token in Chinese online banking"]}]