[{"trad":"廈","simp":"厦","pinyin":"Xia4","defs":["abbr. for Xiamen or Amoy 廈門|厦门[Xia4 men2], Fujian"]},{"trad":"廈","simp":"厦","pinyin":"sha4","defs":["(bound form) tall building; mansion","(bound form) rear annex; lean-to","Taiwan pr. [xia4]"]},{"trad":"廈門","simp":"厦门","pinyin":"Xia4 men2","defs":["see 廈門市|厦门市[Xia4 men2 Shi4]"]},{"trad":"廈門大學","simp":"厦门大学","pinyin":"Xia4 men2 Da4 xue2","defs":["Xiamen University"]},{"trad":"廈門市","simp":"厦门市","pinyin":"Xia4 men2 Shi4","defs":["Xiamen, sub-provincial city in Fujian Province 福建省[Fu2 jian4 Sheng3]"]}]