[{"trad":"悽","simp":"凄","pinyin":"qi1","defs":["variant of 淒|凄[qi1]","sad","mournful"]},{"trad":"悽哀","simp":"凄哀","pinyin":"qi1 ai1","defs":["desolate","mournful"]},{"trad":"悽惻","simp":"凄恻","pinyin":"qi1 ce4","defs":["heartbroken","sorrowful"]},{"trad":"悽愴","simp":"凄怆","pinyin":"qi1 chuang4","defs":["pitiful; painful; heartrending"]},{"trad":"悽慘","simp":"凄惨","pinyin":"qi1 can3","defs":["plaintive","mournful","miserable"]},{"trad":"悽楚","simp":"凄楚","pinyin":"qi1 chu3","defs":["sad; wretched; miserable"]},{"trad":"悽涼","simp":"凄凉","pinyin":"qi1 liang2","defs":["mournful; miserable"]},{"trad":"悽然","simp":"凄然","pinyin":"qi1 ran2","defs":["distressed"]},{"trad":"悽苦","simp":"凄苦","pinyin":"qi1 ku3","defs":["bleak; miserable"]},{"trad":"悽迷","simp":"凄迷","pinyin":"qi1 mi2","defs":["pained and bewildered"]}]