[{"trad":"攻","simp":"攻","pinyin":"gong1","defs":["to attack","to accuse","to study","(LGBT) top"]},{"trad":"攻伐","simp":"攻伐","pinyin":"gong1 fa2","defs":["to attack","to raid","(of medicine) potent"]},{"trad":"攻克","simp":"攻克","pinyin":"gong1 ke4","defs":["to capture","to take","to overcome","to solve"]},{"trad":"攻入","simp":"攻入","pinyin":"gong1 ru4","defs":["to force entrance into","to score a goal (sport)"]},{"trad":"攻其不備","simp":"攻其不备","pinyin":"gong1 qi2 bu4 bei4","defs":["see 出其不意，攻其不備|出其不意，攻其不备[chu1 qi2 bu4 yi4 , gong1 qi2 bu4 bei4]"]},{"trad":"攻其無備","simp":"攻其无备","pinyin":"gong1 qi2 wu2 bei4","defs":["see 出其不意，攻其不備|出其不意，攻其不备[chu1 qi2 bu4 yi4 , gong1 qi2 bu4 bei4]"]},{"trad":"攻勢","simp":"攻势","pinyin":"gong1 shi4","defs":["(military) offensive"]},{"trad":"攻占","simp":"攻占","pinyin":"gong1 zhan4","defs":["to seize control of (an enemy position)","(fig.) to take by storm","to gain (awards, control of a market etc)"]},{"trad":"攻取","simp":"攻取","pinyin":"gong1 qu3","defs":["to attack and seize"]},{"trad":"攻城","simp":"攻城","pinyin":"gong1 cheng2","defs":["to besiege (a town)"]},{"trad":"攻城木","simp":"攻城木","pinyin":"gong1 cheng2 mu4","defs":["battering ram"]},{"trad":"攻城略地","simp":"攻城略地","pinyin":"gong1 cheng2 lu:e4 di4","defs":["to take cities and seize territories (idiom)"]},{"trad":"攻堅","simp":"攻坚","pinyin":"gong1 jian1","defs":["to assault a fortified position","(fig.) to concentrate one's efforts on a particularly difficult part of one's mission"]},{"trad":"攻堅克難","simp":"攻坚克难","pinyin":"gong1 jian1 ke4 nan2","defs":["to tackle a thorny problem and overcome its challenges"]},{"trad":"攻心","simp":"攻心","pinyin":"gong1 xin1","defs":["to mount a psychological attack","to try to demoralize","to try to win over","to try to persuade","(TCM) to fall into a coma or stupor due to an excess of emotion"]},{"trad":"攻打","simp":"攻打","pinyin":"gong1 da3","defs":["to attack (the enemy)"]},{"trad":"攻擊","simp":"攻击","pinyin":"gong1 ji1","defs":["to attack","to accuse","to charge","an attack (terrorist or military)"]},{"trad":"攻擊力","simp":"攻击力","pinyin":"gong1 ji1 li4","defs":["potential for attack","firepower"]},{"trad":"攻擊機","simp":"攻击机","pinyin":"gong1 ji1 ji1","defs":["ground attack aircraft"]},{"trad":"攻擊線","simp":"攻击线","pinyin":"gong1 ji1 xian4","defs":["the front line","the attack (e.g. football forwards)"]},{"trad":"攻滅","simp":"攻灭","pinyin":"gong1 mie4","defs":["to conquer","to defeat (militarily)"]},{"trad":"攻無不克，戰無不勝","simp":"攻无不克，战无不胜","pinyin":"gong1 wu2 bu4 ke4 , zhan4 wu2 bu4 sheng4","defs":["to triumph in every battle and win every fight (idiom); all-conquering","ever victorious","nothing they can't do"]},{"trad":"攻略","simp":"攻略","pinyin":"gong1 lu:e4","defs":["(literary) to storm and capture","strategy; directions; guide; how-to"]},{"trad":"攻砭","simp":"攻砭","pinyin":"gong1 bian1","defs":["to perform acupuncture"]},{"trad":"攻破","simp":"攻破","pinyin":"gong1 po4","defs":["to make a breakthrough","to break through","to breach (military)"]},{"trad":"攻訐","simp":"攻讦","pinyin":"gong1 jie2","defs":["to attack sb by exposing faults","to denounce"]},{"trad":"攻讀","simp":"攻读","pinyin":"gong1 du2","defs":["to major (in a field)","to study a specialty to obtain a higher degree"]},{"trad":"攻關","simp":"攻关","pinyin":"gong1 guan1","defs":["to storm a strategic pass","fig. to tackle a key problem"]},{"trad":"攻防","simp":"攻防","pinyin":"gong1 fang2","defs":["to attack and defend (usu. in reference to opposing sides, but can be one party playing both roles)"]},{"trad":"攻陷","simp":"攻陷","pinyin":"gong1 xian4","defs":["to capture (a fortress, city etc); to take by force"]}]