[{"trad":"棲","simp":"栖","pinyin":"qi1","defs":["to perch","to rest (of birds)","to dwell","to live","to stay"]},{"trad":"棲","simp":"栖","pinyin":"xi1","defs":["used in 棲棲|栖栖[xi1 xi1]"]},{"trad":"棲住","simp":"栖住","pinyin":"qi1 zhu4","defs":["to dwell","to live"]},{"trad":"棲地","simp":"栖地","pinyin":"qi1 di4","defs":["habitat"]},{"trad":"棲居","simp":"栖居","pinyin":"qi1 ju1","defs":["to inhabit; to live in (forests, mountains or wetlands etc)"]},{"trad":"棲息","simp":"栖息","pinyin":"qi1 xi1","defs":["(of a bird) to perch","(of creatures in general) to inhabit; to dwell"]},{"trad":"棲息地","simp":"栖息地","pinyin":"qi1 xi1 di4","defs":["habitat"]},{"trad":"棲木","simp":"栖木","pinyin":"qi1 mu4","defs":["roost","perch"]},{"trad":"棲棲","simp":"栖栖","pinyin":"xi1 xi1","defs":["(literary) restless; unsettled"]},{"trad":"棲棲遑遑","simp":"栖栖遑遑","pinyin":"xi1 xi1 huang2 huang2","defs":["(idiom) restless; unsettled"]},{"trad":"棲身","simp":"栖身","pinyin":"qi1 shen1","defs":["to stay at","to live in (temporarily)"]},{"trad":"棲霞","simp":"栖霞","pinyin":"Qi1 xia2","defs":["see 棲霞市|栖霞市[Qi1 xia2 Shi4]","see 棲霞區|栖霞区[Qi1 xia2 Qu1]"]},{"trad":"棲霞區","simp":"栖霞区","pinyin":"Qi1 xia2 Qu1","defs":["Qixia, a district of Nanjing City 南京市[Nan2 jing1 Shi4], Jiangsu"]},{"trad":"棲霞市","simp":"栖霞市","pinyin":"Qi1 xia2 Shi4","defs":["Qixia, a county-level city in Yantai City 煙台市|烟台市[Yan1 tai2 Shi4], Shandong"]}]