[{"trad":"澆","simp":"浇","pinyin":"jiao1","defs":["to pour liquid","to irrigate (using waterwheel)","to water","to cast (molten metal)","to mold"]},{"trad":"澆冷水","simp":"浇冷水","pinyin":"jiao1 leng3 shui3","defs":["to pour cold water","fig. to discourage"]},{"trad":"澆水","simp":"浇水","pinyin":"jiao1 shui3","defs":["to water (plants etc)"]},{"trad":"澆注","simp":"浇注","pinyin":"jiao1 zhu4","defs":["to pour (molten metal, concrete etc) into a mold"]},{"trad":"澆灌","simp":"浇灌","pinyin":"jiao1 guan4","defs":["to water","to irrigate"]},{"trad":"澆築","simp":"浇筑","pinyin":"jiao1 zhu4","defs":["to pour (concrete etc)"]},{"trad":"澆花","simp":"浇花","pinyin":"jiao1 hua1","defs":["to water the plants","to water the garden"]},{"trad":"澆鑄","simp":"浇铸","pinyin":"jiao1 zhu4","defs":["to cast (molten metal)","to mold"]},{"trad":"澆頭","simp":"浇头","pinyin":"jiao1 tou5","defs":["topping (mixture of ingredients and sauce poured over noodles or rice, esp. in Shanghainese cuisine)"]}]