[{"trad":"紮","simp":"扎","pinyin":"za1","defs":["to tie","to bind","classifier for flowers, banknotes etc: bundle","Taiwan pr. [zha2]"]},{"trad":"紮","simp":"扎","pinyin":"zha1","defs":["(of troops) to be stationed (at)","Taiwan pr. [zha2]"]},{"trad":"紮實","simp":"扎实","pinyin":"zha1 shi5","defs":["variant of 扎實|扎实[zha1 shi5]"]},{"trad":"紮寨","simp":"扎寨","pinyin":"zha1 zhai4","defs":["to set up an encampment"]},{"trad":"紮染","simp":"扎染","pinyin":"za1 ran3","defs":["to tie-dye"]},{"trad":"紮營","simp":"扎营","pinyin":"zha1 ying2","defs":["to camp","to pitch camp","stationed","quartered","Taiwan pr. [zha2 ying2]"]},{"trad":"紮線帶","simp":"扎线带","pinyin":"za1 xian4 dai4","defs":["cable ties","zip ties"]},{"trad":"紮馬剌丁","simp":"扎马剌丁","pinyin":"Za1 ma3 la2 ding1","defs":["Jamal al-Din ibn Muhammad al-Najjari (13th century), famous Persian astronomer and scholar who served Khubilai Khan 忽必烈 from c. 1260"]},{"trad":"紮馬魯丁","simp":"扎马鲁丁","pinyin":"Za1 ma3 lu3 ding1","defs":["see 紮馬剌丁|扎马剌丁[Za1 ma3 la2 ding1]"]}]