[{"trad":"菊","simp":"菊","pinyin":"ju2","defs":["(bound form) chrysanthemum"]},{"trad":"菊池","simp":"菊池","pinyin":"Ju2 chi2","defs":["Kikuchi (Japanese surname and place name)"]},{"trad":"菊科","simp":"菊科","pinyin":"ju2 ke1","defs":["Asteraceae or Compositae (composites), a large family of dicotyledonous plants producing scents, includes aster, daisy and sunflower"]},{"trad":"菊粉","simp":"菊粉","pinyin":"ju2 fen3","defs":["(biochemistry) inulin (aka fructosan)"]},{"trad":"菊糖","simp":"菊糖","pinyin":"ju2 tang2","defs":["(biochemistry) inulin (aka fructosan)"]},{"trad":"菊芋","simp":"菊芋","pinyin":"ju2 yu4","defs":["Jerusalem artichoke"]},{"trad":"菊花","simp":"菊花","pinyin":"ju2 hua1","defs":["chrysanthemum","(TCM) chrysanthemum flower","(slang) anus"]},{"trad":"菊花茶","simp":"菊花茶","pinyin":"ju2 hua1 cha2","defs":["chrysanthemum tea"]},{"trad":"菊苣","simp":"菊苣","pinyin":"ju2 ju4","defs":["chicory"]}]