[{"trad":"陀","simp":"陀","pinyin":"tuo2","defs":["(phonetic)","declivity","steep bank"]},{"trad":"陀思妥也夫斯基","simp":"陀思妥也夫斯基","pinyin":"Tuo2 si1 tuo3 ye3 fu1 si1 ji1","defs":["Fyodor Mikhailovich Dostoevsky (1821-1881), great Russian novelist, author of Crime and Punishment 罪與罰|罪与罚[Zui4 yu3 Fa2]","also written 陀思妥耶夫斯基[Tuo2 si1 tuo3 ye1 fu1 si1 ji1]"]},{"trad":"陀思妥耶夫斯基","simp":"陀思妥耶夫斯基","pinyin":"Tuo2 si1 tuo3 ye1 fu1 si1 ji1","defs":["Fyodor Mikhailovich Dostoevsky (1821-1881), great Russian novelist, author of Crime and Punishment 罪與罰|罪与罚[Zui4 yu3 Fa2]"]},{"trad":"陀羅尼","simp":"陀罗尼","pinyin":"tuo2 luo2 ni2","defs":["incantation (Sanskrit: dharani)","religious chant (promoting virtue and obstructing evil)"]},{"trad":"陀螺","simp":"陀螺","pinyin":"tuo2 luo2","defs":["spinning top","gyroscope"]},{"trad":"陀螺儀","simp":"陀螺仪","pinyin":"tuo2 luo2 yi2","defs":["gyroscope"]}]